{"skeleton":{"hash":"GAy13Ri6Nb1zqAeWjlMG+HZ4hTo","spine":"3.0.09","width":560,"height":446,"images":"./capsule/"},"bones":[{"name":"root"},{"name":"center","parent":"root"},{"name":"body","parent":"center","length":34.02,"x":1.32,"y":-100.84,"rotation":84.55},{"name":"r_leg","parent":"body","length":15.74,"x":11.55,"y":-16.24,"rotation":158.12},{"name":"r_arm","parent":"body","length":26.73,"x":31.63,"y":-16.99,"rotation":-70.48},{"name":"l_leg","parent":"body","length":14.74,"x":-2.2,"y":9.12,"rotation":177.74},{"name":"l_arm","parent":"body","length":22.07,"x":22.88,"y":18.85,"rotation":79.73},{"name":"head","parent":"body","length":45.27,"x":34.24,"y":4.59,"rotation":9.38,"color":"33009bff"},{"name":"h2_acc3","parent":"head","x":54.19,"y":-29.89,"color":"33009bff"},{"name":"h3_acc3","parent":"h2_acc3","length":23.58,"x":-11.4,"y":21.47,"rotation":-4.6,"color":"33009bff"},{"name":"h1_o1_acc3","parent":"head","x":30.24,"y":-0.1,"color":"33009bff"},{"name":"bone","parent":"head","x":8.62,"y":30.6},{"name":"att","parent":"root"},{"name":"tail","parent":"body","length":28.92,"x":9.22,"y":-19.79,"rotation":-93.6}],"slots":[{"name":"water_capsule_att","bone":"att"},{"name":"water_capsule_tail","bone":"tail","attachment":"water_capsule_tail"},{"name":"water_capsule_leftarm","bone":"l_arm","attachment":"water_capsule_leftarm"},{"name":"water_capsule_leftleg","bone":"l_leg","attachment":"water_capsule_leftleg"},{"name":"water_capsule_body","bone":"body","attachment":"water_capsule_body"},{"name":"body","bone":"body"},{"name":"water_capsule_head","bone":"head","attachment":"water_capsule_head"},{"name":"water_capsule_eye","bone":"head","attachment":"water_capsule_eye"},{"name":"water_capsule_rightarm","bone":"r_arm","attachment":"water_capsule_rightarm"},{"name":"water_capsule_rightleg","bone":"r_leg","attachment":"water_capsule_rightleg"},{"name":"water_capsule_acc","bone":"bone"},{"name":"head","bone":"head"},{"name":"h1_g2_acc3","bone":"head"},{"name":"h1_l1_acc3","bone":"head"},{"name":"h1_o1_acc3","bone":"h1_o1_acc3"},{"name":"h1_o2_acc3","bone":"head"},{"name":"h1_r1_acc3","bone":"head"},{"name":"h1_s2_acc3","bone":"head"},{"name":"h2_acc3","bone":"h2_acc3"},{"name":"h3_acc3","bone":"h3_acc3"},{"name":"att","bone":"att","attachment":"acc3_att_back"}],"skins":{"default":{"att":{"acc3_att_back":{"x":9.94,"y":91.71,"width":560,"height":446}},"body":{"body_acc3":{"x":20.92,"y":-1.88,"rotation":-84.56,"width":56,"height":58}},"h1_g2_acc3":{"h1_g2_acc3":{"x":26.52,"y":30.48,"rotation":-93.95,"width":38,"height":28}},"h1_l1_acc3":{"h1_l1_acc3":{"x":35.18,"y":-18.95,"rotation":-93.95,"width":16,"height":37}},"h1_o1_acc3":{"h1_o1_acc3":{"x":-0.16,"rotation":-93.95,"width":29,"height":29}},"h1_o2_acc3":{"h1_o2_acc3":{"x":30.08,"y":-0.1,"rotation":-93.95,"width":21,"height":21}},"h1_r1_acc3":{"h1_r1_acc3":{"x":55.84,"y":8.47,"rotation":-93.95,"width":25,"height":26}},"h1_s2_acc3":{"h1_s2_acc3":{"x":47.03,"y":27.33,"rotation":-93.95,"width":43,"height":22}},"h2_acc3":{"h2_acc3":{"x":-1.53,"y":10.22,"rotation":-93.95,"width":48,"height":35}},"h3_acc3":{"h3_acc3":{"x":10.87,"y":-0.08,"rotation":-89.37,"width":49,"height":49}},"head":{"haed_acc3":{"x":45.09,"y":-6.02,"rotation":-93.95,"width":110,"height":97}},"water_capsule_acc":{"water_capsule_acc":{"x":-9.84,"y":-7.17,"rotation":-93.95,"width":41,"height":22}},"water_capsule_att":{"att_acc3":{"x":-40.08,"y":-32.84,"width":142,"height":162},"water_capsule_att":{"x":-33.86,"y":-33.2,"width":146,"height":161}},"water_capsule_body":{"water_capsule_body":{"x":19.54,"y":-2.14,"rotation":-84.55,"width":54,"height":52}},"water_capsule_eye":{"water_capsule_eye":{"x":42.82,"y":-6.28,"rotation":-93.94,"width":94,"height":99}},"water_capsule_head":{"head2_acc3":{"x":37.31,"y":-6.45,"rotation":-93.95,"width":95,"height":89},"water_capsule_head":{"x":42.82,"y":-6.28,"rotation":-93.94,"width":94,"height":99}},"water_capsule_leftarm":{"l_wing_acc3":{"x":7.1,"y":1.49,"rotation":-164.28,"width":51,"height":32},"water_capsule_leftarm":{"x":6.75,"y":0.51,"rotation":-164.29,"width":49,"height":31}},"water_capsule_leftleg":{"l_leg_acc3":{"x":5.2,"y":1.17,"rotation":97.69,"width":31,"height":39},"water_capsule_leftleg":{"x":4.51,"y":1.28,"rotation":97.69,"width":30,"height":38}},"water_capsule_rightarm":{"r_wing_acc3":{"x":15.1,"y":-7.27,"rotation":-14.06,"width":43,"height":39},"water_capsule_rightarm":{"x":15.29,"y":-7.25,"rotation":-14.07,"width":42,"height":37}},"water_capsule_rightleg":{"r_leg_acc3":{"x":14.01,"y":2.33,"rotation":117.31,"width":37,"height":35},"water_capsule_rightleg":{"x":13.03,"y":2.25,"rotation":117.31,"width":36,"height":33}},"water_capsule_tail":{"water_capsule_tail":{"x":17.54,"y":2.78,"rotation":9.04,"width":50,"height":22}}}},"animations":{"acc":{"slots":{"att":{"attachment":[{"time":0,"name":null},{"time":4.6666,"name":null}]},"body":{"attachment":[{"time":0,"name":null},{"time":4.6666,"name":null}]},"h1_g2_acc3":{"attachment":[{"time":0,"name":null},{"time":4.6666,"name":null}]},"h1_l1_acc3":{"attachment":[{"time":0,"name":null},{"time":4.6666,"name":null}]},"h1_o1_acc3":{"attachment":[{"time":0,"name":null},{"time":4.6666,"name":null}]},"h1_o2_acc3":{"attachment":[{"time":0,"name":null},{"time":4.6666,"name":null}]},"h1_r1_acc3":{"attachment":[{"time":0,"name":null},{"time":4.6666,"name":null}]},"h1_s2_acc3":{"attachment":[{"time":0,"name":null},{"time":4.6666,"name":null}]},"h2_acc3":{"attachment":[{"time":0,"name":null},{"time":4.6666,"name":null}]},"h3_acc3":{"attachment":[{"time":0,"name":null},{"time":4.6666,"name":null}]},"head":{"attachment":[{"time":0,"name":null},{"time":4.6666,"name":null}]},"water_capsule_acc":{"attachment":[{"time":0,"name":"water_capsule_acc"},{"time":4.6666,"name":"water_capsule_acc"}]},"water_capsule_att":{"attachment":[{"time":0,"name":null},{"time":2.3333,"name":null},{"time":4.6666,"name":null}]},"water_capsule_body":{"attachment":[{"time":0,"name":"water_capsule_body"},{"time":2.3333,"name":"water_capsule_body"},{"time":4.6666,"name":"water_capsule_body"}]},"water_capsule_eye":{"attachment":[{"time":0,"name":"water_capsule_eye"},{"time":1.6333,"name":null},{"time":1.7333,"name":"water_capsule_eye"},{"time":1.8333,"name":null},{"time":1.9333,"name":"water_capsule_eye"},{"time":2.3333,"name":"water_capsule_eye"},{"time":4.6666,"name":"water_capsule_eye"}]},"water_capsule_head":{"attachment":[{"time":0,"name":"water_capsule_head"},{"time":2.3333,"name":"water_capsule_head"},{"time":4.6666,"name":"water_capsule_head"}]},"water_capsule_leftarm":{"attachment":[{"time":0,"name":"water_capsule_leftarm"},{"time":2.3333,"name":"water_capsule_leftarm"},{"time":4.6666,"name":"water_capsule_leftarm"}]},"water_capsule_leftleg":{"attachment":[{"time":0,"name":"water_capsule_leftleg"},{"time":2.3333,"name":"water_capsule_leftleg"},{"time":4.6666,"name":"water_capsule_leftleg"}]},"water_capsule_rightarm":{"attachment":[{"time":0,"name":"water_capsule_rightarm"},{"time":2.3333,"name":"water_capsule_rightarm"},{"time":4.6666,"name":"water_capsule_rightarm"}]},"water_capsule_rightleg":{"attachment":[{"time":0,"name":"water_capsule_rightleg"},{"time":2.3333,"name":"water_capsule_rightleg"},{"time":4.6666,"name":"water_capsule_rightleg"}]},"water_capsule_tail":{"attachment":[{"time":0,"name":"water_capsule_tail"},{"time":2.3333,"name":"water_capsule_tail"},{"time":4.6666,"name":"water_capsule_tail"}]}},"bones":{"body":{"rotate":[{"time":0,"angle":0},{"time":1.1666,"angle":14.03},{"time":2.3333,"angle":0},{"time":3.5,"angle":14.03},{"time":4.6666,"angle":0}],"translate":[{"time":0,"x":0,"y":0},{"time":1.1666,"x":0,"y":17.85},{"time":2.3333,"x":0,"y":0},{"time":3.5,"x":0,"y":17.85},{"time":4.6666,"x":0,"y":0}],"scale":[{"time":0,"x":1,"y":1,"curve":"stepped"},{"time":2.3333,"x":1,"y":1,"curve":"stepped"},{"time":4.6666,"x":1,"y":1}]},"head":{"rotate":[{"time":0,"angle":0},{"time":1.1666,"angle":-17.01},{"time":2.3333,"angle":0},{"time":3.5,"angle":-17.01},{"time":4.6666,"angle":0}],"translate":[{"time":0,"x":0,"y":0,"curve":"stepped"},{"time":2.3333,"x":0,"y":0,"curve":"stepped"},{"time":4.6666,"x":0,"y":0}],"scale":[{"time":0,"x":1,"y":1,"curve":"stepped"},{"time":2.3333,"x":1,"y":1,"curve":"stepped"},{"time":4.6666,"x":1,"y":1}]},"h1_o1_acc3":{"rotate":[{"time":0,"angle":0,"curve":"stepped"},{"time":4.6666,"angle":0}],"translate":[{"time":0,"x":0,"y":0,"curve":"stepped"},{"time":4.6666,"x":0,"y":0}],"scale":[{"time":0,"x":1,"y":1,"curve":"stepped"},{"time":4.6666,"x":1,"y":1}]},"h2_acc3":{"rotate":[{"time":0,"angle":0,"curve":"stepped"},{"time":4.6666,"angle":0}],"translate":[{"time":0,"x":0,"y":0,"curve":"stepped"},{"time":4.6666,"x":0,"y":0}],"scale":[{"time":0,"x":1,"y":1,"curve":"stepped"},{"time":4.6666,"x":1,"y":1}]},"h3_acc3":{"rotate":[{"time":0,"angle":0,"curve":"stepped"},{"time":4.6666,"angle":0}],"translate":[{"time":0,"x":0,"y":0,"curve":"stepped"},{"time":4.6666,"x":0,"y":0}],"scale":[{"time":0,"x":1,"y":1,"curve":"stepped"},{"time":4.6666,"x":1,"y":1}]},"bone":{"rotate":[{"time":0,"angle":0,"curve":"stepped"},{"time":4.6666,"angle":0}],"translate":[{"time":0,"x":0,"y":0,"curve":"stepped"},{"time":4.6666,"x":0,"y":0}],"scale":[{"time":0,"x":1,"y":1,"curve":"stepped"},{"time":4.6666,"x":1,"y":1}]},"att":{"rotate":[{"time":0,"angle":0,"curve":"stepped"},{"time":2.3333,"angle":0,"curve":"stepped"},{"time":4.6666,"angle":0}],"translate":[{"time":0,"x":0,"y":0,"curve":"stepped"},{"time":2.3333,"x":0,"y":0,"curve":"stepped"},{"time":4.6666,"x":0,"y":0}],"scale":[{"time":0,"x":1,"y":1,"curve":"stepped"},{"time":2.3333,"x":1,"y":1,"curve":"stepped"},{"time":4.6666,"x":1,"y":1}]},"l_arm":{"rotate":[{"time":0,"angle":0},{"time":0.5,"angle":-36.25},{"time":1,"angle":19.29},{"time":1.5,"angle":-36.25},{"time":1.9,"angle":19.29},{"time":2.3333,"angle":0},{"time":2.8333,"angle":-36.25},{"time":3.3333,"angle":19.29},{"time":3.8333,"angle":-36.25},{"time":4.2333,"angle":19.29},{"time":4.6666,"angle":0}],"translate":[{"time":0,"x":0,"y":0,"curve":"stepped"},{"time":2.3333,"x":0,"y":0,"curve":"stepped"},{"time":4.6666,"x":0,"y":0}],"scale":[{"time":0,"x":1,"y":1},{"time":1,"x":1.286,"y":0.951},{"time":2.3333,"x":1,"y":1},{"time":3.3333,"x":1.286,"y":0.951},{"time":4.6666,"x":1,"y":1}]},"l_leg":{"rotate":[{"time":0,"angle":0},{"time":1.1666,"angle":-332.05},{"time":2.3333,"angle":0},{"time":3.5,"angle":-332.05},{"time":4.6666,"angle":0}],"translate":[{"time":0,"x":0,"y":0,"curve":"stepped"},{"time":2.3333,"x":0,"y":0,"curve":"stepped"},{"time":4.6666,"x":0,"y":0}],"scale":[{"time":0,"x":1,"y":1,"curve":"stepped"},{"time":2.3333,"x":1,"y":1,"curve":"stepped"},{"time":4.6666,"x":1,"y":1}]},"r_arm":{"rotate":[{"time":0,"angle":0},{"time":0.5,"angle":32.72},{"time":1,"angle":-36.4},{"time":1.5,"angle":32.72},{"time":1.9,"angle":-23.24},{"time":2.3333,"angle":0},{"time":2.8333,"angle":32.72},{"time":3.3333,"angle":-36.4},{"time":3.8333,"angle":32.72},{"time":4.2333,"angle":-23.24},{"time":4.6666,"angle":0}],"translate":[{"time":0,"x":0,"y":0},{"time":1,"x":-3.22,"y":0.37},{"time":2.3333,"x":0,"y":0},{"time":3.3333,"x":-3.22,"y":0.37},{"time":4.6666,"x":0,"y":0}],"scale":[{"time":0,"x":1,"y":1},{"time":1,"x":1.198,"y":0.936},{"time":2.3333,"x":1,"y":1},{"time":3.3333,"x":1.198,"y":0.936},{"time":4.6666,"x":1,"y":1}]},"r_leg":{"rotate":[{"time":0,"angle":0},{"time":1.1666,"angle":-18.37},{"time":2.3333,"angle":0},{"time":3.5,"angle":-18.37},{"time":4.6666,"angle":0}],"translate":[{"time":0,"x":0,"y":0},{"time":1.1666,"x":-0.2,"y":2.15},{"time":2.3333,"x":0,"y":0},{"time":3.5,"x":-0.2,"y":2.15},{"time":4.6666,"x":0,"y":0}],"scale":[{"time":0,"x":1,"y":1,"curve":"stepped"},{"time":2.3333,"x":1,"y":1,"curve":"stepped"},{"time":4.6666,"x":1,"y":1}]},"tail":{"rotate":[{"time":0,"angle":0},{"time":0.3333,"angle":268.21},{"time":0.6666,"angle":197.61},{"time":1.5,"angle":-7.93},{"time":1.9,"angle":-39.68},{"time":2.3333,"angle":0},{"time":3.5,"angle":318.56},{"time":4.6666,"angle":0}],"translate":[{"time":0,"x":0,"y":0},{"time":0.3333,"x":0.35,"y":7.78,"curve":"stepped"},{"time":0.6666,"x":0.35,"y":7.78},{"time":2.3333,"x":0,"y":0},{"time":3.5,"x":-2.78,"y":7.64},{"time":4.6666,"x":0,"y":0}],"scale":[{"time":0,"x":1,"y":1,"curve":"stepped"},{"time":2.3333,"x":1,"y":1,"curve":"stepped"},{"time":4.6666,"x":1,"y":1}]},"root":{"rotate":[{"time":0,"angle":0,"curve":"stepped"},{"time":2.3333,"angle":0,"curve":"stepped"},{"time":4.6666,"angle":0}],"translate":[{"time":0,"x":0,"y":0,"curve":"stepped"},{"time":2.3333,"x":0,"y":0,"curve":"stepped"},{"time":4.6666,"x":0,"y":0}],"scale":[{"time":0,"x":1,"y":1,"curve":"stepped"},{"time":2.3333,"x":1,"y":1,"curve":"stepped"},{"time":4.6666,"x":1,"y":1}]},"center":{"rotate":[{"time":0,"angle":0,"curve":"stepped"},{"time":2.3333,"angle":0,"curve":"stepped"},{"time":4.6666,"angle":0}],"translate":[{"time":0,"x":0,"y":0,"curve":"stepped"},{"time":2.3333,"x":0,"y":0,"curve":"stepped"},{"time":4.6666,"x":0,"y":0}],"scale":[{"time":0,"x":1,"y":1,"curve":"stepped"},{"time":2.3333,"x":1,"y":1,"curve":"stepped"},{"time":4.6666,"x":1,"y":1}]}},"drawOrder":[{"time":0},{"time":4.6666}]},"acc3":{"slots":{"att":{"attachment":[{"time":0,"name":null},{"time":4.6666,"name":null}]},"body":{"attachment":[{"time":0,"name":"body_acc3"},{"time":2.3333,"name":"body_acc3"},{"time":4.6666,"name":"body_acc3"}]},"h1_g2_acc3":{"attachment":[{"time":0,"name":"h1_g2_acc3"},{"time":2.3333,"name":"h1_g2_acc3"},{"time":4.6666,"name":"h1_g2_acc3"}],"color":[{"time":0,"color":"ffffffff"},{"time":0.5333,"color":"ffffffa4"},{"time":1.0333,"color":"ffffffff","curve":"stepped"},{"time":2.3333,"color":"ffffffff"},{"time":3.1333,"color":"ffffffac"},{"time":3.8333,"color":"ffffffff","curve":"stepped"},{"time":4.6666,"color":"ffffffff"}]},"h1_l1_acc3":{"attachment":[{"time":0,"name":"h1_l1_acc3"},{"time":2.3333,"name":"h1_l1_acc3"},{"time":4.6666,"name":"h1_l1_acc3"}],"color":[{"time":0,"color":"ffffffff","curve":"stepped"},{"time":0.5333,"color":"ffffffff","curve":"stepped"},{"time":1.4,"color":"ffffffff"},{"time":1.7333,"color":"ffffffa7"},{"time":3.1,"color":"ffffffcc"},{"time":3.7333,"color":"ffffffff","curve":"stepped"},{"time":4.6666,"color":"ffffffff"}]},"h1_o1_acc3":{"attachment":[{"time":0,"name":"h1_o1_acc3"},{"time":2.3333,"name":"h1_o1_acc3"},{"time":4.6666,"name":"h1_o1_acc3"}],"color":[{"time":0,"color":"ffffffff"},{"time":1.1,"color":"ffffff74"},{"time":2,"color":"ffffff61"},{"time":2.3333,"color":"ffffffff","curve":"stepped"},{"time":3,"color":"ffffffff"},{"time":3.2333,"color":"ffffffa3"},{"time":3.9666,"color":"ffffffa0"},{"time":4.3666,"color":"ffffffff","curve":"stepped"},{"time":4.6666,"color":"ffffffff"}]},"h1_o2_acc3":{"attachment":[{"time":0,"name":"h1_o2_acc3"},{"time":2.3333,"name":"h1_o2_acc3"},{"time":4.6666,"name":"h1_o2_acc3"}],"color":[{"time":0,"color":"ffffffff"},{"time":0.7666,"color":"ffffffaa"},{"time":1.3666,"color":"ffffffff"},{"time":2.6666,"color":"ffffff8d"},{"time":2.8,"color":"ffffffff","curve":"stepped"},{"time":3.7333,"color":"ffffffff","curve":"stepped"},{"time":4.6666,"color":"ffffffff"}]},"h1_r1_acc3":{"attachment":[{"time":0,"name":"h1_r1_acc3"},{"time":2.3333,"name":"h1_r1_acc3"},{"time":4.6666,"name":"h1_r1_acc3"}],"color":[{"time":0,"color":"ffffffff","curve":"stepped"},{"time":0.5666,"color":"ffffffff"},{"time":1.1333,"color":"ffffff86"},{"time":1.5666,"color":"ffffffff"},{"time":1.9,"color":"ffffff9e"},{"time":2.0666,"color":"ffffff9f"},{"time":2.1666,"color":"ffffffff"},{"time":3.3,"color":"ffffff9f"},{"time":3.6333,"color":"ffffffff","curve":"stepped"},{"time":3.9333,"color":"ffffffff","curve":"stepped"},{"time":4.1,"color":"ffffffff"},{"time":4.3666,"color":"ffffff97"},{"time":4.6666,"color":"ffffffff"}]},"h1_s2_acc3":{"attachment":[{"time":0,"name":"h1_s2_acc3"},{"time":2.3333,"name":"h1_s2_acc3"},{"time":4.6666,"name":"h1_s2_acc3"}],"color":[{"time":0,"color":"ffffffff","curve":"stepped"},{"time":0.5333,"color":"ffffffff"},{"time":0.7666,"color":"ffffff92"},{"time":1.0333,"color":"ffffffff","curve":"stepped"},{"time":3.2,"color":"ffffffff"},{"time":3.4333,"color":"ffffff76"},{"time":3.7,"color":"ffffffff","curve":"stepped"},{"time":4.3333,"color":"ffffffff"},{"time":4.4666,"color":"ffffffba"},{"time":4.6666,"color":"ffffffff"}]},"h2_acc3":{"attachment":[{"time":0,"name":"h2_acc3"},{"time":2.3333,"name":"h2_acc3"},{"time":4.6666,"name":"h2_acc3"}],"color":[{"time":0,"color":"ffffffff","curve":"stepped"},{"time":1.1666,"color":"ffffffff","curve":"stepped"},{"time":2.3333,"color":"ffffffff"},{"time":2.4666,"color":"ffffff00","curve":"stepped"},{"time":3.1666,"color":"ffffff00"},{"time":3.2333,"color":"ffffffff","curve":"stepped"},{"time":4.6666,"color":"ffffffff"}]},"h3_acc3":{"attachment":[{"time":0,"name":"h3_acc3"},{"time":2.3333,"name":"h3_acc3"},{"time":4.6666,"name":"h3_acc3"}],"color":[{"time":0,"color":"ffffffff","curve":"stepped"},{"time":2.3333,"color":"ffffffff"},{"time":2.4666,"color":"ffffff00","curve":"stepped"},{"time":3.1666,"color":"ffffff00"},{"time":3.2666,"color":"ffffffff","curve":"stepped"},{"time":4.6666,"color":"ffffffff"}]},"head":{"attachment":[{"time":0,"name":"haed_acc3"},{"time":2.3333,"name":"haed_acc3"},{"time":4.6666,"name":"haed_acc3"}]},"water_capsule_acc":{"attachment":[{"time":0,"name":null},{"time":2.3333,"name":null},{"time":4.6666,"name":null}]},"water_capsule_att":{"attachment":[{"time":0,"name":null},{"time":2.3333,"name":null},{"time":4.6666,"name":null}]},"water_capsule_body":{"attachment":[{"time":0,"name":"water_capsule_body"},{"time":2.3333,"name":"water_capsule_body"},{"time":4.6666,"name":"water_capsule_body"}]},"water_capsule_eye":{"attachment":[{"time":0,"name":"water_capsule_eye"},{"time":1.6333,"name":null},{"time":1.7333,"name":"water_capsule_eye"},{"time":1.8333,"name":null},{"time":1.9333,"name":"water_capsule_eye"},{"time":2.3333,"name":"water_capsule_eye"},{"time":4.6666,"name":"water_capsule_eye"}]},"water_capsule_head":{"attachment":[{"time":0,"name":"head2_acc3"},{"time":2.3333,"name":"head2_acc3"},{"time":4.6666,"name":"head2_acc3"}]},"water_capsule_leftarm":{"attachment":[{"time":0,"name":"l_wing_acc3"},{"time":2.3333,"name":"l_wing_acc3"},{"time":4.6666,"name":"l_wing_acc3"}]},"water_capsule_leftleg":{"attachment":[{"time":0,"name":"l_leg_acc3"},{"time":2.3333,"name":"l_leg_acc3"},{"time":4.6666,"name":"l_leg_acc3"}]},"water_capsule_rightarm":{"attachment":[{"time":0,"name":"r_wing_acc3"},{"time":2.3333,"name":"r_wing_acc3"},{"time":4.6666,"name":"r_wing_acc3"}]},"water_capsule_rightleg":{"attachment":[{"time":0,"name":"r_leg_acc3"},{"time":2.3333,"name":"r_leg_acc3"},{"time":4.6666,"name":"r_leg_acc3"}]},"water_capsule_tail":{"attachment":[{"time":0,"name":"water_capsule_tail"},{"time":2.3333,"name":"water_capsule_tail"},{"time":4.6666,"name":"water_capsule_tail"}]}},"bones":{"body":{"rotate":[{"time":0,"angle":0},{"time":1.1666,"angle":14.03},{"time":2.3333,"angle":0},{"time":3.5,"angle":14.03},{"time":4.6666,"angle":0}],"translate":[{"time":0,"x":0,"y":0},{"time":1.1666,"x":0,"y":17.85},{"time":2.3333,"x":0,"y":0},{"time":3.5,"x":0,"y":17.85},{"time":4.6666,"x":0,"y":0}],"scale":[{"time":0,"x":1,"y":1,"curve":"stepped"},{"time":2.3333,"x":1,"y":1,"curve":"stepped"},{"time":4.6666,"x":1,"y":1}]},"head":{"rotate":[{"time":0,"angle":0},{"time":1.1666,"angle":-17.01},{"time":2.3333,"angle":0},{"time":3.5,"angle":-17.01},{"time":4.6666,"angle":0}],"translate":[{"time":0,"x":0,"y":0,"curve":"stepped"},{"time":2.3333,"x":0,"y":0,"curve":"stepped"},{"time":4.6666,"x":0,"y":0}],"scale":[{"time":0,"x":1,"y":1,"curve":"stepped"},{"time":2.3333,"x":1,"y":1,"curve":"stepped"},{"time":4.6666,"x":1,"y":1}]},"h1_o1_acc3":{"rotate":[{"time":0,"angle":0},{"time":1.1,"angle":20.12},{"time":1.5333,"angle":14.8},{"time":2,"angle":28.13},{"time":2.3333,"angle":0},{"time":3,"angle":-15.36},{"time":3.2333,"angle":-14.55},{"time":3.9666,"angle":-26.11},{"time":4.6666,"angle":0}],"translate":[{"time":0,"x":0,"y":0,"curve":"stepped"},{"time":2.3333,"x":0,"y":0,"curve":"stepped"},{"time":4.6666,"x":0,"y":0}],"scale":[{"time":0,"x":1,"y":1,"curve":"stepped"},{"time":2.3333,"x":1,"y":1,"curve":"stepped"},{"time":4.6666,"x":1,"y":1}]},"h2_acc3":{"rotate":[{"time":0,"angle":0,"curve":"stepped"},{"time":2.3333,"angle":0,"curve":"stepped"},{"time":4.6666,"angle":0}],"translate":[{"time":0,"x":0,"y":0,"curve":"stepped"},{"time":2.3333,"x":0,"y":0,"curve":"stepped"},{"time":4.6666,"x":0,"y":0}],"scale":[{"time":0,"x":1,"y":1,"curve":"stepped"},{"time":2.3333,"x":1,"y":1,"curve":"stepped"},{"time":4.6666,"x":1,"y":1}]},"h3_acc3":{"rotate":[{"time":0,"angle":0,"curve":"stepped"},{"time":2.3333,"angle":0,"curve":"stepped"},{"time":4.6666,"angle":0}],"translate":[{"time":0,"x":0,"y":0,"curve":"stepped"},{"time":2.3333,"x":0,"y":0,"curve":"stepped"},{"time":4.6666,"x":0,"y":0}],"scale":[{"time":0,"x":1,"y":1,"curve":"stepped"},{"time":2.3333,"x":1,"y":1},{"time":2.4666,"x":1,"y":-0.023,"curve":"stepped"},{"time":3.1666,"x":1,"y":-0.023},{"time":3.3333,"x":1,"y":1.226},{"time":3.4,"x":1,"y":1,"curve":"stepped"},{"time":4.6666,"x":1,"y":1}]},"bone":{"rotate":[{"time":0,"angle":0,"curve":"stepped"},{"time":2.3333,"angle":0,"curve":"stepped"},{"time":4.6666,"angle":0}],"translate":[{"time":0,"x":0,"y":0,"curve":"stepped"},{"time":2.3333,"x":0,"y":0,"curve":"stepped"},{"time":4.6666,"x":0,"y":0}],"scale":[{"time":0,"x":1,"y":1,"curve":"stepped"},{"time":2.3333,"x":1,"y":1,"curve":"stepped"},{"time":4.6666,"x":1,"y":1}]},"att":{"rotate":[{"time":0,"angle":0,"curve":"stepped"},{"time":2.3333,"angle":0,"curve":"stepped"},{"time":4.6666,"angle":0}],"translate":[{"time":0,"x":0,"y":0,"curve":"stepped"},{"time":2.3333,"x":0,"y":0,"curve":"stepped"},{"time":4.6666,"x":0,"y":0}],"scale":[{"time":0,"x":1,"y":1,"curve":"stepped"},{"time":2.3333,"x":1,"y":1,"curve":"stepped"},{"time":4.6666,"x":1,"y":1}]},"l_arm":{"rotate":[{"time":0,"angle":0},{"time":0.5,"angle":-36.25},{"time":1,"angle":19.29},{"time":1.5,"angle":-36.25},{"time":1.9,"angle":19.29},{"time":2.3333,"angle":0},{"time":2.8333,"angle":-36.25},{"time":3.3333,"angle":19.29},{"time":3.8333,"angle":-36.25},{"time":4.2333,"angle":19.29},{"time":4.6666,"angle":0}],"translate":[{"time":0,"x":0,"y":0,"curve":"stepped"},{"time":2.3333,"x":0,"y":0,"curve":"stepped"},{"time":4.6666,"x":0,"y":0}],"scale":[{"time":0,"x":1,"y":1},{"time":1,"x":1.286,"y":0.951},{"time":2.3333,"x":1,"y":1},{"time":3.3333,"x":1.286,"y":0.951},{"time":4.6666,"x":1,"y":1}]},"l_leg":{"rotate":[{"time":0,"angle":0},{"time":1.1666,"angle":-332.05},{"time":2.3333,"angle":0},{"time":3.5,"angle":-332.05},{"time":4.6666,"angle":0}],"translate":[{"time":0,"x":0,"y":0,"curve":"stepped"},{"time":2.3333,"x":0,"y":0,"curve":"stepped"},{"time":4.6666,"x":0,"y":0}],"scale":[{"time":0,"x":1,"y":1,"curve":"stepped"},{"time":2.3333,"x":1,"y":1,"curve":"stepped"},{"time":4.6666,"x":1,"y":1}]},"r_arm":{"rotate":[{"time":0,"angle":0},{"time":0.5,"angle":32.72},{"time":1,"angle":-43.8},{"time":1.5,"angle":32.72},{"time":1.9,"angle":-23.24},{"time":2.3333,"angle":0},{"time":2.8333,"angle":32.72},{"time":3.3333,"angle":-43.8},{"time":3.8333,"angle":32.72},{"time":4.2333,"angle":-23.24},{"time":4.6666,"angle":0}],"translate":[{"time":0,"x":-3.95,"y":-2.56},{"time":1,"x":-7.13,"y":-2.33},{"time":2.3333,"x":-3.95,"y":-2.56},{"time":3.3333,"x":-7.13,"y":-2.33},{"time":4.6666,"x":-3.95,"y":-2.56}],"scale":[{"time":0,"x":1,"y":1},{"time":1,"x":1.198,"y":0.936},{"time":2.3333,"x":1,"y":1},{"time":3.3333,"x":1.198,"y":0.936},{"time":4.6666,"x":1,"y":1}]},"r_leg":{"rotate":[{"time":0,"angle":0},{"time":1.1666,"angle":-18.37},{"time":2.3333,"angle":0},{"time":3.5,"angle":-18.37},{"time":4.6666,"angle":0}],"translate":[{"time":0,"x":0,"y":0},{"time":1.1666,"x":-0.2,"y":2.15},{"time":2.3333,"x":0,"y":0},{"time":3.5,"x":-0.2,"y":2.15},{"time":4.6666,"x":0,"y":0}],"scale":[{"time":0,"x":1,"y":1,"curve":"stepped"},{"time":2.3333,"x":1,"y":1,"curve":"stepped"},{"time":4.6666,"x":1,"y":1}]},"tail":{"rotate":[{"time":0,"angle":0},{"time":0.3333,"angle":268.21},{"time":0.6666,"angle":197.61},{"time":1.5,"angle":-7.93},{"time":1.9,"angle":-39.68},{"time":2.3333,"angle":0},{"time":3.5,"angle":318.56},{"time":4.6666,"angle":0}],"translate":[{"time":0,"x":0,"y":0},{"time":0.3333,"x":0.35,"y":7.78,"curve":"stepped"},{"time":0.6666,"x":0.35,"y":7.78},{"time":2.3333,"x":0,"y":0},{"time":3.5,"x":-2.78,"y":7.64},{"time":4.6666,"x":0,"y":0}],"scale":[{"time":0,"x":1,"y":1,"curve":"stepped"},{"time":2.3333,"x":1,"y":1,"curve":"stepped"},{"time":4.6666,"x":1,"y":1}]},"root":{"rotate":[{"time":0,"angle":0,"curve":"stepped"},{"time":2.3333,"angle":0,"curve":"stepped"},{"time":4.6666,"angle":0}],"translate":[{"time":0,"x":0,"y":0,"curve":"stepped"},{"time":2.3333,"x":0,"y":0,"curve":"stepped"},{"time":4.6666,"x":0,"y":0}],"scale":[{"time":0,"x":1,"y":1,"curve":"stepped"},{"time":2.3333,"x":1,"y":1,"curve":"stepped"},{"time":4.6666,"x":1,"y":1}]},"center":{"rotate":[{"time":0,"angle":0,"curve":"stepped"},{"time":2.3333,"angle":0,"curve":"stepped"},{"time":4.6666,"angle":0}],"translate":[{"time":0,"x":0,"y":0,"curve":"stepped"},{"time":2.3333,"x":0,"y":0,"curve":"stepped"},{"time":4.6666,"x":0,"y":0}],"scale":[{"time":0,"x":1,"y":1,"curve":"stepped"},{"time":2.3333,"x":1,"y":1,"curve":"stepped"},{"time":4.6666,"x":1,"y":1}]}},"drawOrder":[{"time":0},{"time":2.3333,"offsets":[{"slot":"water_capsule_rightarm","offset":3}]},{"time":4.6666}]},"acc3_att":{"slots":{"att":{"attachment":[{"time":0,"name":"acc3_att_back"}]},"body":{"attachment":[{"time":0,"name":null}]},"h1_g2_acc3":{"attachment":[{"time":0,"name":null}]},"h1_l1_acc3":{"attachment":[{"time":0,"name":null}]},"h1_o1_acc3":{"attachment":[{"time":0,"name":null}]},"h1_o2_acc3":{"attachment":[{"time":0,"name":null}]},"h1_r1_acc3":{"attachment":[{"time":0,"name":null}]},"h1_s2_acc3":{"attachment":[{"time":0,"name":null}]},"h2_acc3":{"attachment":[{"time":0,"name":null}]},"h3_acc3":{"attachment":[{"time":0,"name":null}]},"head":{"attachment":[{"time":0,"name":null}]},"water_capsule_acc":{"attachment":[{"time":0,"name":null}]},"water_capsule_att":{"attachment":[{"time":0,"name":"att_acc3"}]},"water_capsule_body":{"attachment":[{"time":0,"name":null}]},"water_capsule_eye":{"attachment":[{"time":0,"name":null}]},"water_capsule_head":{"attachment":[{"time":0,"name":null}]},"water_capsule_leftarm":{"attachment":[{"time":0,"name":null}]},"water_capsule_leftleg":{"attachment":[{"time":0,"name":null}]},"water_capsule_rightarm":{"attachment":[{"time":0,"name":null}]},"water_capsule_rightleg":{"attachment":[{"time":0,"name":null}]},"water_capsule_tail":{"attachment":[{"time":0,"name":null}]}},"bones":{"body":{"rotate":[{"time":0,"angle":0}],"translate":[{"time":0,"x":0,"y":0}],"scale":[{"time":0,"x":1,"y":1}]},"head":{"rotate":[{"time":0,"angle":0}],"translate":[{"time":0,"x":0,"y":0}],"scale":[{"time":0,"x":1,"y":1}]},"h1_o1_acc3":{"rotate":[{"time":0,"angle":0}],"translate":[{"time":0,"x":0,"y":0}],"scale":[{"time":0,"x":1,"y":1}]},"h2_acc3":{"rotate":[{"time":0,"angle":0}],"translate":[{"time":0,"x":0,"y":0}],"scale":[{"time":0,"x":1,"y":1}]},"h3_acc3":{"rotate":[{"time":0,"angle":0}],"translate":[{"time":0,"x":0,"y":0}],"scale":[{"time":0,"x":1,"y":1}]},"bone":{"rotate":[{"time":0,"angle":0}],"translate":[{"time":0,"x":10.29,"y":40.78}],"scale":[{"time":0,"x":1,"y":1}]},"att":{"rotate":[{"time":0,"angle":0}],"translate":[{"time":0,"x":0,"y":0}],"scale":[{"time":0,"x":1,"y":1}]},"l_arm":{"rotate":[{"time":0,"angle":0}],"translate":[{"time":0,"x":0,"y":0}],"scale":[{"time":0,"x":1,"y":1}]},"l_leg":{"rotate":[{"time":0,"angle":0}],"translate":[{"time":0,"x":0,"y":0}],"scale":[{"time":0,"x":1,"y":1}]},"r_arm":{"rotate":[{"time":0,"angle":0}],"translate":[{"time":0,"x":0,"y":0}],"scale":[{"time":0,"x":1,"y":1}]},"r_leg":{"rotate":[{"time":0,"angle":0}],"translate":[{"time":0,"x":0,"y":0}],"scale":[{"time":0,"x":1,"y":1}]},"tail":{"rotate":[{"time":0,"angle":0}],"translate":[{"time":0,"x":0,"y":0}],"scale":[{"time":0,"x":1,"y":1}]},"root":{"rotate":[{"time":0,"angle":0}],"translate":[{"time":0,"x":0,"y":0}],"scale":[{"time":0,"x":1,"y":1}]},"center":{"rotate":[{"time":0,"angle":0}],"translate":[{"time":0,"x":0,"y":0}],"scale":[{"time":0,"x":1,"y":1}]}},"drawOrder":[{"time":0,"offsets":[{"slot":"att","offset":-20}]}]},"acc_att":{"slots":{"att":{"attachment":[{"time":0,"name":null}]},"body":{"attachment":[{"time":0,"name":null}]},"h1_g2_acc3":{"attachment":[{"time":0,"name":null}]},"h1_l1_acc3":{"attachment":[{"time":0,"name":null}]},"h1_o1_acc3":{"attachment":[{"time":0,"name":null}]},"h1_o2_acc3":{"attachment":[{"time":0,"name":null}]},"h1_r1_acc3":{"attachment":[{"time":0,"name":null}]},"h1_s2_acc3":{"attachment":[{"time":0,"name":null}]},"h2_acc3":{"attachment":[{"time":0,"name":null}]},"h3_acc3":{"attachment":[{"time":0,"name":null}]},"head":{"attachment":[{"time":0,"name":null}]},"water_capsule_acc":{"attachment":[{"time":0,"name":"water_capsule_acc"}]},"water_capsule_att":{"attachment":[{"time":0,"name":"water_capsule_att"}]},"water_capsule_body":{"attachment":[{"time":0,"name":null}]},"water_capsule_eye":{"attachment":[{"time":0,"name":null}]},"water_capsule_head":{"attachment":[{"time":0,"name":null}]},"water_capsule_leftarm":{"attachment":[{"time":0,"name":null}]},"water_capsule_leftleg":{"attachment":[{"time":0,"name":null}]},"water_capsule_rightarm":{"attachment":[{"time":0,"name":null}]},"water_capsule_rightleg":{"attachment":[{"time":0,"name":null}]},"water_capsule_tail":{"attachment":[{"time":0,"name":null}]}},"bones":{"body":{"rotate":[{"time":0,"angle":0}],"translate":[{"time":0,"x":0,"y":0}],"scale":[{"time":0,"x":1,"y":1}]},"head":{"rotate":[{"time":0,"angle":0}],"translate":[{"time":0,"x":0,"y":0}],"scale":[{"time":0,"x":1,"y":1}]},"h1_o1_acc3":{"rotate":[{"time":0,"angle":0}],"translate":[{"time":0,"x":0,"y":0}],"scale":[{"time":0,"x":1,"y":1}]},"h2_acc3":{"rotate":[{"time":0,"angle":0}],"translate":[{"time":0,"x":0,"y":0}],"scale":[{"time":0,"x":1,"y":1}]},"h3_acc3":{"rotate":[{"time":0,"angle":0}],"translate":[{"time":0,"x":0,"y":0}],"scale":[{"time":0,"x":1,"y":1}]},"bone":{"rotate":[{"time":0,"angle":0}],"translate":[{"time":0,"x":10.29,"y":40.78}],"scale":[{"time":0,"x":1,"y":1}]},"att":{"rotate":[{"time":0,"angle":0}],"translate":[{"time":0,"x":0,"y":-10.81}],"scale":[{"time":0,"x":1,"y":1}]},"l_arm":{"rotate":[{"time":0,"angle":0}],"translate":[{"time":0,"x":0,"y":0}],"scale":[{"time":0,"x":1,"y":1}]},"l_leg":{"rotate":[{"time":0,"angle":0}],"translate":[{"time":0,"x":0,"y":0}],"scale":[{"time":0,"x":1,"y":1}]},"r_arm":{"rotate":[{"time":0,"angle":0}],"translate":[{"time":0,"x":0,"y":0}],"scale":[{"time":0,"x":1,"y":1}]},"r_leg":{"rotate":[{"time":0,"angle":0}],"translate":[{"time":0,"x":0,"y":0}],"scale":[{"time":0,"x":1,"y":1}]},"tail":{"rotate":[{"time":0,"angle":0}],"translate":[{"time":0,"x":0,"y":0}],"scale":[{"time":0,"x":1,"y":1}]},"root":{"rotate":[{"time":0,"angle":0}],"translate":[{"time":0,"x":0,"y":0}],"scale":[{"time":0,"x":1,"y":1}]},"center":{"rotate":[{"time":0,"angle":0}],"translate":[{"time":0,"x":0,"y":0}],"scale":[{"time":0,"x":1,"y":1}]}},"drawOrder":[{"time":0}]},"att":{"slots":{"att":{"attachment":[{"time":0,"name":null}]},"body":{"attachment":[{"time":0,"name":null}]},"h1_g2_acc3":{"attachment":[{"time":0,"name":null}]},"h1_l1_acc3":{"attachment":[{"time":0,"name":null}]},"h1_o1_acc3":{"attachment":[{"time":0,"name":null}]},"h1_o2_acc3":{"attachment":[{"time":0,"name":null}]},"h1_r1_acc3":{"attachment":[{"time":0,"name":null}]},"h1_s2_acc3":{"attachment":[{"time":0,"name":null}]},"h2_acc3":{"attachment":[{"time":0,"name":null}]},"h3_acc3":{"attachment":[{"time":0,"name":null}]},"head":{"attachment":[{"time":0,"name":null}]},"water_capsule_acc":{"attachment":[{"time":0,"name":null}]},"water_capsule_att":{"attachment":[{"time":0,"name":"water_capsule_att"}]},"water_capsule_body":{"attachment":[{"time":0,"name":null}]},"water_capsule_eye":{"attachment":[{"time":0,"name":null}]},"water_capsule_head":{"attachment":[{"time":0,"name":null}]},"water_capsule_leftarm":{"attachment":[{"time":0,"name":null}]},"water_capsule_leftleg":{"attachment":[{"time":0,"name":null}]},"water_capsule_rightarm":{"attachment":[{"time":0,"name":null}]},"water_capsule_rightleg":{"attachment":[{"time":0,"name":null}]},"water_capsule_tail":{"attachment":[{"time":0,"name":null}]}},"bones":{"body":{"rotate":[{"time":0,"angle":0}],"translate":[{"time":0,"x":0,"y":0}],"scale":[{"time":0,"x":1,"y":1}]},"head":{"rotate":[{"time":0,"angle":0}],"translate":[{"time":0,"x":0,"y":0}],"scale":[{"time":0,"x":1,"y":1}]},"h1_o1_acc3":{"rotate":[{"time":0,"angle":0}],"translate":[{"time":0,"x":0,"y":0}],"scale":[{"time":0,"x":1,"y":1}]},"h2_acc3":{"rotate":[{"time":0,"angle":0}],"translate":[{"time":0,"x":0,"y":0}],"scale":[{"time":0,"x":1,"y":1}]},"h3_acc3":{"rotate":[{"time":0,"angle":0}],"translate":[{"time":0,"x":0,"y":0}],"scale":[{"time":0,"x":1,"y":1}]},"bone":{"rotate":[{"time":0,"angle":0}],"translate":[{"time":0,"x":10.29,"y":40.78}],"scale":[{"time":0,"x":1,"y":1}]},"att":{"rotate":[{"time":0,"angle":0}],"translate":[{"time":0,"x":0,"y":-10.81}],"scale":[{"time":0,"x":1,"y":1}]},"l_arm":{"rotate":[{"time":0,"angle":0}],"translate":[{"time":0,"x":0,"y":0}],"scale":[{"time":0,"x":1,"y":1}]},"l_leg":{"rotate":[{"time":0,"angle":0}],"translate":[{"time":0,"x":0,"y":0}],"scale":[{"time":0,"x":1,"y":1}]},"r_arm":{"rotate":[{"time":0,"angle":0}],"translate":[{"time":0,"x":0,"y":0}],"scale":[{"time":0,"x":1,"y":1}]},"r_leg":{"rotate":[{"time":0,"angle":0}],"translate":[{"time":0,"x":0,"y":0}],"scale":[{"time":0,"x":1,"y":1}]},"tail":{"rotate":[{"time":0,"angle":0}],"translate":[{"time":0,"x":0,"y":0}],"scale":[{"time":0,"x":1,"y":1}]},"root":{"rotate":[{"time":0,"angle":0}],"translate":[{"time":0,"x":0,"y":0}],"scale":[{"time":0,"x":1,"y":1}]},"center":{"rotate":[{"time":0,"angle":0}],"translate":[{"time":0,"x":0,"y":0}],"scale":[{"time":0,"x":1,"y":1}]}},"drawOrder":[{"time":0}]},"wait":{"slots":{"att":{"attachment":[{"time":0,"name":null},{"time":4.6666,"name":null}]},"body":{"attachment":[{"time":0,"name":null},{"time":4.6666,"name":null}]},"h1_g2_acc3":{"attachment":[{"time":0,"name":null},{"time":4.6666,"name":null}]},"h1_l1_acc3":{"attachment":[{"time":0,"name":null},{"time":4.6666,"name":null}]},"h1_o1_acc3":{"attachment":[{"time":0,"name":null},{"time":4.6666,"name":null}]},"h1_o2_acc3":{"attachment":[{"time":0,"name":null},{"time":4.6666,"name":null}]},"h1_r1_acc3":{"attachment":[{"time":0,"name":null},{"time":4.6666,"name":null}]},"h1_s2_acc3":{"attachment":[{"time":0,"name":null},{"time":4.6666,"name":null}]},"h2_acc3":{"attachment":[{"time":0,"name":null},{"time":4.6666,"name":null}]},"h3_acc3":{"attachment":[{"time":0,"name":null},{"time":4.6666,"name":null}]},"head":{"attachment":[{"time":0,"name":null},{"time":4.6666,"name":null}]},"water_capsule_acc":{"attachment":[{"time":0,"name":null},{"time":4.6666,"name":null}]},"water_capsule_att":{"attachment":[{"time":0,"name":null},{"time":2.3333,"name":null},{"time":4.6666,"name":null}]},"water_capsule_body":{"attachment":[{"time":0,"name":"water_capsule_body"},{"time":2.3333,"name":"water_capsule_body"},{"time":4.6666,"name":"water_capsule_body"}]},"water_capsule_eye":{"attachment":[{"time":0,"name":"water_capsule_eye"},{"time":1.6333,"name":null},{"time":1.7333,"name":"water_capsule_eye"},{"time":1.8333,"name":null},{"time":1.9333,"name":"water_capsule_eye"},{"time":2.3333,"name":"water_capsule_eye"},{"time":4.6666,"name":"water_capsule_eye"}]},"water_capsule_head":{"attachment":[{"time":0,"name":"water_capsule_head"},{"time":2.3333,"name":"water_capsule_head"},{"time":4.6666,"name":"water_capsule_head"}]},"water_capsule_leftarm":{"attachment":[{"time":0,"name":"water_capsule_leftarm"},{"time":2.3333,"name":"water_capsule_leftarm"},{"time":4.6666,"name":"water_capsule_leftarm"}]},"water_capsule_leftleg":{"attachment":[{"time":0,"name":"water_capsule_leftleg"},{"time":2.3333,"name":"water_capsule_leftleg"},{"time":4.6666,"name":"water_capsule_leftleg"}]},"water_capsule_rightarm":{"attachment":[{"time":0,"name":"water_capsule_rightarm"},{"time":2.3333,"name":"water_capsule_rightarm"},{"time":4.6666,"name":"water_capsule_rightarm"}]},"water_capsule_rightleg":{"attachment":[{"time":0,"name":"water_capsule_rightleg"},{"time":2.3333,"name":"water_capsule_rightleg"},{"time":4.6666,"name":"water_capsule_rightleg"}]},"water_capsule_tail":{"attachment":[{"time":0,"name":"water_capsule_tail"},{"time":2.3333,"name":"water_capsule_tail"},{"time":4.6666,"name":"water_capsule_tail"}]}},"bones":{"body":{"rotate":[{"time":0,"angle":0},{"time":1.1666,"angle":14.03},{"time":2.3333,"angle":0},{"time":3.5,"angle":14.03},{"time":4.6666,"angle":0}],"translate":[{"time":0,"x":0,"y":0},{"time":1.1666,"x":0,"y":17.85},{"time":2.3333,"x":0,"y":0},{"time":3.5,"x":0,"y":17.85},{"time":4.6666,"x":0,"y":0}],"scale":[{"time":0,"x":1,"y":1,"curve":"stepped"},{"time":2.3333,"x":1,"y":1,"curve":"stepped"},{"time":4.6666,"x":1,"y":1}]},"head":{"rotate":[{"time":0,"angle":0},{"time":1.1666,"angle":-17.01},{"time":2.3333,"angle":0},{"time":3.5,"angle":-17.01},{"time":4.6666,"angle":0}],"translate":[{"time":0,"x":0,"y":0,"curve":"stepped"},{"time":2.3333,"x":0,"y":0,"curve":"stepped"},{"time":4.6666,"x":0,"y":0}],"scale":[{"time":0,"x":1,"y":1,"curve":"stepped"},{"time":2.3333,"x":1,"y":1,"curve":"stepped"},{"time":4.6666,"x":1,"y":1}]},"h1_o1_acc3":{"rotate":[{"time":4.6666,"angle":0}],"translate":[{"time":4.6666,"x":0,"y":0}],"scale":[{"time":4.6666,"x":1,"y":1}]},"h2_acc3":{"rotate":[{"time":4.6666,"angle":0}],"translate":[{"time":4.6666,"x":0,"y":0}],"scale":[{"time":4.6666,"x":1,"y":1}]},"h3_acc3":{"rotate":[{"time":4.6666,"angle":0}],"translate":[{"time":4.6666,"x":0,"y":0}],"scale":[{"time":4.6666,"x":1,"y":1}]},"bone":{"rotate":[{"time":0,"angle":0,"curve":"stepped"},{"time":4.6666,"angle":0}],"translate":[{"time":0,"x":0,"y":0,"curve":"stepped"},{"time":4.6666,"x":0,"y":0}],"scale":[{"time":0,"x":1,"y":1,"curve":"stepped"},{"time":4.6666,"x":1,"y":1}]},"att":{"rotate":[{"time":0,"angle":0,"curve":"stepped"},{"time":2.3333,"angle":0,"curve":"stepped"},{"time":4.6666,"angle":0}],"translate":[{"time":0,"x":0,"y":-3.31,"curve":"stepped"},{"time":2.3333,"x":0,"y":0,"curve":"stepped"},{"time":4.6666,"x":1.1,"y":-2.2}],"scale":[{"time":0,"x":1,"y":1,"curve":"stepped"},{"time":2.3333,"x":1,"y":1,"curve":"stepped"},{"time":4.6666,"x":1,"y":1}]},"l_arm":{"rotate":[{"time":0,"angle":0},{"time":0.5,"angle":-36.25},{"time":1,"angle":19.29},{"time":1.5,"angle":-36.25},{"time":1.9,"angle":19.29},{"time":2.3333,"angle":0},{"time":2.8333,"angle":-36.25},{"time":3.3333,"angle":19.29},{"time":3.8333,"angle":-36.25},{"time":4.2333,"angle":19.29},{"time":4.6666,"angle":0}],"translate":[{"time":0,"x":0,"y":0,"curve":"stepped"},{"time":2.3333,"x":0,"y":0,"curve":"stepped"},{"time":4.6666,"x":0,"y":0}],"scale":[{"time":0,"x":1,"y":1},{"time":1,"x":1.286,"y":0.951},{"time":2.3333,"x":1,"y":1},{"time":3.3333,"x":1.286,"y":0.951},{"time":4.6666,"x":1,"y":1}]},"l_leg":{"rotate":[{"time":0,"angle":0},{"time":1.1666,"angle":-332.05},{"time":2.3333,"angle":0},{"time":3.5,"angle":-332.05},{"time":4.6666,"angle":0}],"translate":[{"time":0,"x":0,"y":0,"curve":"stepped"},{"time":2.3333,"x":0,"y":0,"curve":"stepped"},{"time":4.6666,"x":0,"y":0}],"scale":[{"time":0,"x":1,"y":1,"curve":"stepped"},{"time":2.3333,"x":1,"y":1,"curve":"stepped"},{"time":4.6666,"x":1,"y":1}]},"r_arm":{"rotate":[{"time":0,"angle":0},{"time":0.5,"angle":32.72},{"time":1,"angle":-36.4},{"time":1.5,"angle":32.72},{"time":1.9,"angle":-23.24},{"time":2.3333,"angle":0},{"time":2.8333,"angle":32.72},{"time":3.3333,"angle":-36.4},{"time":3.8333,"angle":32.72},{"time":4.2333,"angle":-23.24},{"time":4.6666,"angle":0}],"translate":[{"time":0,"x":0,"y":0},{"time":1,"x":-3.22,"y":0.37},{"time":2.3333,"x":0,"y":0},{"time":3.3333,"x":-3.22,"y":0.37},{"time":4.6666,"x":0,"y":0}],"scale":[{"time":0,"x":1,"y":1},{"time":1,"x":1.198,"y":0.936},{"time":2.3333,"x":1,"y":1},{"time":3.3333,"x":1.198,"y":0.936},{"time":4.6666,"x":1,"y":1}]},"r_leg":{"rotate":[{"time":0,"angle":0},{"time":1.1666,"angle":-18.37},{"time":2.3333,"angle":0},{"time":3.5,"angle":-18.37},{"time":4.6666,"angle":0}],"translate":[{"time":0,"x":0,"y":0},{"time":1.1666,"x":-0.2,"y":2.15},{"time":2.3333,"x":0,"y":0},{"time":3.5,"x":-0.2,"y":2.15},{"time":4.6666,"x":0,"y":0}],"scale":[{"time":0,"x":1,"y":1,"curve":"stepped"},{"time":2.3333,"x":1,"y":1,"curve":"stepped"},{"time":4.6666,"x":1,"y":1}]},"tail":{"rotate":[{"time":0,"angle":0},{"time":0.3333,"angle":268.21},{"time":0.6666,"angle":197.61},{"time":1.5,"angle":-7.93},{"time":1.9,"angle":-39.68},{"time":2.3333,"angle":0},{"time":3.5,"angle":318.56},{"time":4.6666,"angle":0}],"translate":[{"time":0,"x":0,"y":0},{"time":0.3333,"x":0.35,"y":7.78,"curve":"stepped"},{"time":0.6666,"x":0.35,"y":7.78},{"time":2.3333,"x":0,"y":0},{"time":3.5,"x":-2.78,"y":7.64},{"time":4.6666,"x":0,"y":0}],"scale":[{"time":0,"x":1,"y":1,"curve":"stepped"},{"time":2.3333,"x":1,"y":1,"curve":"stepped"},{"time":4.6666,"x":1,"y":1}]},"root":{"rotate":[{"time":0,"angle":0,"curve":"stepped"},{"time":2.3333,"angle":0,"curve":"stepped"},{"time":4.6666,"angle":0}],"translate":[{"time":0,"x":0,"y":0,"curve":"stepped"},{"time":2.3333,"x":0,"y":0,"curve":"stepped"},{"time":4.6666,"x":0,"y":0}],"scale":[{"time":0,"x":1,"y":1,"curve":"stepped"},{"time":2.3333,"x":1,"y":1,"curve":"stepped"},{"time":4.6666,"x":1,"y":1}]},"center":{"rotate":[{"time":0,"angle":0,"curve":"stepped"},{"time":2.3333,"angle":0,"curve":"stepped"},{"time":4.6666,"angle":0}],"translate":[{"time":0,"x":0,"y":0,"curve":"stepped"},{"time":2.3333,"x":0,"y":0,"curve":"stepped"},{"time":4.6666,"x":0,"y":0}],"scale":[{"time":0,"x":1,"y":1,"curve":"stepped"},{"time":2.3333,"x":1,"y":1,"curve":"stepped"},{"time":4.6666,"x":1,"y":1}]}},"drawOrder":[{"time":0},{"time":4.6666}]}}}