{"bones":[{"name":"root"},{"name":"bone","parent":"root"},{"name":"bone2","parent":"bone","x":-9.03,"y":-6.2},{"name":"bone3","parent":"bone","length":30.51,"x":26.89,"y":-26.94,"rotation":73.75},{"name":"bone5","parent":"bone","length":30.51,"x":-29.68,"y":-26.94,"rotation":73.75},{"name":"bone4","parent":"bone3","x":6.39,"y":1.15,"rotation":-73.75},{"name":"bone6","parent":"bone5","x":6.75,"y":0.48,"rotation":-73.75}],"slots":[{"name":"dragon_pet_wind6a_armor2","bone":"bone5","attachment":"dragon_pet_wind6a_armor"},{"name":"dragon_pet_wind6a_hand2","bone":"bone6","attachment":"dragon_pet_wind6a_hand2"},{"name":"dragon_pet_wind6a_body","bone":"bone","attachment":"dragon_pet_wind6a_body"},{"name":"dragon_pet_wind6a_eye","bone":"bone2","attachment":"dragon_pet_wind6a_eye"},{"name":"dragon_pet_wind6a_hand1","bone":"bone4","attachment":"dragon_pet_wind6a_hand1"},{"name":"dragon_pet_wind6a_armor","bone":"bone3","attachment":"dragon_pet_wind6a_armor"},{"name":"bone","bone":"bone"}],"skins":{"default":{"bone":{"dragon_pet_wind6a_att":{"x":1.35,"y":1.34,"width":100,"height":100}},"dragon_pet_wind6a_armor":{"dragon_pet_wind6a_armor":{"x":19.49,"y":0.81,"rotation":-73.75,"width":20,"height":49}},"dragon_pet_wind6a_armor2":{"dragon_pet_wind6a_armor":{"x":19.49,"y":0.81,"rotation":-73.75,"width":20,"height":49}},"dragon_pet_wind6a_body":{"dragon_pet_wind6a_body":{"x":-0.06,"y":1.51,"width":75,"height":84}},"dragon_pet_wind6a_eye":{"dragon_pet_wind6a_eye":{"x":3.81,"y":3.4,"width":39,"height":21}},"dragon_pet_wind6a_hand1":{"dragon_pet_wind6a_hand1":{"x":-0.99,"y":-1.74,"width":24,"height":34}},"dragon_pet_wind6a_hand2":{"dragon_pet_wind6a_hand2":{"x":-0.47,"y":-1.29,"width":24,"height":35}}}},"animations":{"att":{"bones":{"bone":{"rotate":[{"time":0,"angle":0}],"translate":[{"time":0,"x":0,"y":0}],"scale":[{"time":0,"x":1,"y":1}]},"bone2":{"rotate":[{"time":0,"angle":0}],"translate":[{"time":0,"x":0,"y":0}],"scale":[{"time":0,"x":1,"y":1}]},"bone4":{"rotate":[{"time":0,"angle":0}],"translate":[{"time":0,"x":0,"y":0}],"scale":[{"time":0,"x":1,"y":1}]},"bone5":{"rotate":[{"time":0,"angle":0}],"translate":[{"time":0,"x":0,"y":0}],"scale":[{"time":0,"x":1,"y":1}]},"root":{"rotate":[{"time":0,"angle":0}],"translate":[{"time":0,"x":0,"y":0}],"scale":[{"time":0,"x":1,"y":1}]},"bone3":{"rotate":[{"time":0,"angle":0}],"translate":[{"time":0,"x":0,"y":0}],"scale":[{"time":0,"x":1,"y":1}]},"bone6":{"rotate":[{"time":0,"angle":0}],"translate":[{"time":0,"x":0,"y":0}],"scale":[{"time":0,"x":1,"y":1}]}},"slots":{"bone":{"attachment":[{"time":0,"name":"dragon_pet_wind6a_att"}]},"dragon_pet_wind6a_armor":{"attachment":[{"time":0,"name":null}]},"dragon_pet_wind6a_armor2":{"attachment":[{"time":0,"name":null}]},"dragon_pet_wind6a_body":{"attachment":[{"time":0,"name":null}]},"dragon_pet_wind6a_eye":{"attachment":[{"time":0,"name":null}]},"dragon_pet_wind6a_hand1":{"attachment":[{"time":0,"name":null}]},"dragon_pet_wind6a_hand2":{"attachment":[{"time":0,"name":null}]}}},"wait":{"bones":{"bone6":{"rotate":[{"time":0,"angle":0},{"time":0.1458,"angle":90},{"time":0.2916,"angle":180},{"time":0.4375,"angle":270},{"time":0.5833,"angle":0},{"time":0.7291,"angle":90},{"time":0.875,"angle":180},{"time":1.0208,"angle":270},{"time":1.1666,"angle":0},{"time":1.3125,"angle":90},{"time":1.4583,"angle":180},{"time":1.6041,"angle":270},{"time":1.75,"angle":0},{"time":1.8958,"angle":90},{"time":2.0416,"angle":180},{"time":2.1875,"angle":270},{"time":2.3333,"angle":0},{"time":2.4791,"angle":90},{"time":2.625,"angle":180},{"time":2.7708,"angle":270},{"time":2.9166,"angle":0},{"time":3.0625,"angle":90},{"time":3.2083,"angle":180},{"time":3.3541,"angle":270},{"time":3.5,"angle":0},{"time":3.6458,"angle":90},{"time":3.7916,"angle":180},{"time":3.9375,"angle":270},{"time":4.0833,"angle":0},{"time":4.2291,"angle":90},{"time":4.375,"angle":180},{"time":4.5208,"angle":270},{"time":4.6666,"angle":360}],"translate":[{"time":0,"x":0,"y":0},{"time":1.1666,"x":-1.19,"y":-0.34},{"time":2.3333,"x":0,"y":0},{"time":3.5,"x":-1.19,"y":-0.34},{"time":4.6666,"x":0,"y":0}],"scale":[{"time":0,"x":1,"y":1},{"time":0.1458,"x":1.5,"y":0.5},{"time":0.2916,"x":1,"y":1},{"time":0.4375,"x":1.5,"y":0.5},{"time":0.5833,"x":1,"y":1},{"time":0.7291,"x":1.5,"y":0.5},{"time":0.875,"x":1,"y":1},{"time":1.0208,"x":1.5,"y":0.5},{"time":1.1666,"x":1,"y":1},{"time":1.3125,"x":1.5,"y":0.5},{"time":1.4583,"x":1,"y":1},{"time":1.6041,"x":1.5,"y":0.5},{"time":1.75,"x":1,"y":1},{"time":1.8958,"x":1.5,"y":0.5},{"time":2.0416,"x":1,"y":1},{"time":2.1875,"x":1.5,"y":0.5},{"time":2.3333,"x":1,"y":1},{"time":2.4791,"x":1.5,"y":0.5},{"time":2.625,"x":1,"y":1},{"time":2.7708,"x":1.5,"y":0.5},{"time":2.9166,"x":1,"y":1},{"time":3.0625,"x":1.5,"y":0.5},{"time":3.2083,"x":1,"y":1},{"time":3.3541,"x":1.5,"y":0.5},{"time":3.5,"x":1,"y":1},{"time":3.6458,"x":1.5,"y":0.5},{"time":3.7916,"x":1,"y":1},{"time":3.9375,"x":1.5,"y":0.5},{"time":4.0833,"x":1,"y":1},{"time":4.2291,"x":1.5,"y":0.5},{"time":4.375,"x":1,"y":1},{"time":4.5208,"x":1.5,"y":0.5},{"time":4.6666,"x":1,"y":1}]},"bone5":{"rotate":[{"time":0,"angle":0,"curve":"stepped"},{"time":1.1666,"angle":0,"curve":"stepped"},{"time":2.3333,"angle":0,"curve":"stepped"},{"time":3.5,"angle":0,"curve":"stepped"},{"time":4.6666,"angle":0}],"translate":[{"time":0,"x":0,"y":0},{"time":1.1666,"x":-2.17,"y":1.45},{"time":2.3333,"x":0,"y":0},{"time":3.5,"x":-2.17,"y":1.45},{"time":4.6666,"x":0,"y":0}],"scale":[{"time":0,"x":1,"y":1,"curve":"stepped"},{"time":1.1666,"x":1,"y":1,"curve":"stepped"},{"time":2.3333,"x":1,"y":1,"curve":"stepped"},{"time":3.5,"x":1,"y":1,"curve":"stepped"},{"time":4.6666,"x":1,"y":1}]},"bone4":{"rotate":[{"time":0,"angle":0},{"time":0.1458,"angle":90},{"time":0.2916,"angle":180},{"time":0.4375,"angle":270},{"time":0.5833,"angle":0},{"time":0.7291,"angle":90},{"time":0.875,"angle":180},{"time":1.0208,"angle":270},{"time":1.1666,"angle":0},{"time":1.3125,"angle":90},{"time":1.4583,"angle":180},{"time":1.6041,"angle":270},{"time":1.75,"angle":0},{"time":1.8958,"angle":90},{"time":2.0416,"angle":180},{"time":2.1875,"angle":270},{"time":2.3333,"angle":0},{"time":2.4791,"angle":90},{"time":2.625,"angle":180},{"time":2.7708,"angle":270},{"time":2.9166,"angle":0},{"time":3.0625,"angle":90},{"time":3.2083,"angle":180},{"time":3.3541,"angle":270},{"time":3.5,"angle":0},{"time":3.6458,"angle":90},{"time":3.7916,"angle":180},{"time":3.9375,"angle":270},{"time":4.0833,"angle":0},{"time":4.2291,"angle":90},{"time":4.375,"angle":180},{"time":4.5208,"angle":270},{"time":4.6666,"angle":360}],"translate":[{"time":0,"x":0,"y":0},{"time":1.1666,"x":-2.12,"y":-0.51},{"time":2.3333,"x":0,"y":0},{"time":3.5,"x":-2.12,"y":-0.51},{"time":4.6666,"x":0,"y":0}],"scale":[{"time":0,"x":1,"y":1},{"time":0.1458,"x":1.5,"y":0.5},{"time":0.2916,"x":1,"y":1},{"time":0.4375,"x":1.5,"y":0.5},{"time":0.5833,"x":1,"y":1},{"time":0.7291,"x":1.5,"y":0.5},{"time":0.875,"x":1,"y":1},{"time":1.0208,"x":1.5,"y":0.5},{"time":1.1666,"x":1,"y":1},{"time":1.3125,"x":1.5,"y":0.5},{"time":1.4583,"x":1,"y":1},{"time":1.6041,"x":1.5,"y":0.5},{"time":1.75,"x":1,"y":1},{"time":1.8958,"x":1.5,"y":0.5},{"time":2.0416,"x":1,"y":1},{"time":2.1875,"x":1.5,"y":0.5},{"time":2.3333,"x":1,"y":1},{"time":2.4791,"x":1.5,"y":0.5},{"time":2.625,"x":1,"y":1},{"time":2.7708,"x":1.5,"y":0.5},{"time":2.9166,"x":1,"y":1},{"time":3.0625,"x":1.5,"y":0.5},{"time":3.2083,"x":1,"y":1},{"time":3.3541,"x":1.5,"y":0.5},{"time":3.5,"x":1,"y":1},{"time":3.6458,"x":1.5,"y":0.5},{"time":3.7916,"x":1,"y":1},{"time":3.9375,"x":1.5,"y":0.5},{"time":4.0833,"x":1,"y":1},{"time":4.2291,"x":1.5,"y":0.5},{"time":4.375,"x":1,"y":1},{"time":4.5208,"x":1.5,"y":0.5},{"time":4.6666,"x":1,"y":1}]},"bone3":{"rotate":[{"time":0,"angle":0},{"time":1.1666,"angle":2.7},{"time":2.3333,"angle":0},{"time":3.5,"angle":2.7},{"time":4.6666,"angle":0}],"translate":[{"time":0,"x":0,"y":0},{"time":1.1666,"x":3.15,"y":3.02},{"time":2.3333,"x":0,"y":0},{"time":3.5,"x":3.15,"y":3.02},{"time":4.6666,"x":0,"y":0}],"scale":[{"time":0,"x":1,"y":1,"curve":"stepped"},{"time":1.1666,"x":1,"y":1,"curve":"stepped"},{"time":2.3333,"x":1,"y":1,"curve":"stepped"},{"time":3.5,"x":1,"y":1,"curve":"stepped"},{"time":4.6666,"x":1,"y":1}]},"bone2":{"rotate":[{"time":0,"angle":0,"curve":"stepped"},{"time":1.1666,"angle":0,"curve":"stepped"},{"time":2.3333,"angle":0,"curve":"stepped"},{"time":3.5,"angle":0,"curve":"stepped"},{"time":4.6666,"angle":0}],"translate":[{"time":0,"x":0,"y":0,"curve":"stepped"},{"time":1.1666,"x":0,"y":0,"curve":"stepped"},{"time":2.3333,"x":0,"y":0,"curve":"stepped"},{"time":3.5,"x":0,"y":0,"curve":"stepped"},{"time":4.6666,"x":0,"y":0}],"scale":[{"time":0,"x":1,"y":1,"curve":"stepped"},{"time":1.1666,"x":1,"y":1,"curve":"stepped"},{"time":2.3333,"x":1,"y":1,"curve":"stepped"},{"time":3.5,"x":1,"y":1,"curve":"stepped"},{"time":4.6666,"x":1,"y":1}]},"bone":{"rotate":[{"time":0,"angle":0,"curve":"stepped"},{"time":1.1666,"angle":0,"curve":"stepped"},{"time":2.3333,"angle":0,"curve":"stepped"},{"time":3.5,"angle":0,"curve":"stepped"},{"time":4.6666,"angle":0}],"translate":[{"time":0,"x":0,"y":0},{"time":1.1666,"x":0,"y":-10},{"time":2.3333,"x":0,"y":0},{"time":3.5,"x":0,"y":-10},{"time":4.6666,"x":0,"y":0}],"scale":[{"time":0,"x":1,"y":1,"curve":"stepped"},{"time":1.1666,"x":1,"y":1,"curve":"stepped"},{"time":2.3333,"x":1,"y":1,"curve":"stepped"},{"time":3.5,"x":1,"y":1,"curve":"stepped"},{"time":4.6666,"x":1,"y":1}]},"root":{"rotate":[{"time":0,"angle":0,"curve":"stepped"},{"time":1.1666,"angle":0,"curve":"stepped"},{"time":2.3333,"angle":0,"curve":"stepped"},{"time":3.5,"angle":0,"curve":"stepped"},{"time":4.6666,"angle":0}],"translate":[{"time":0,"x":0,"y":0,"curve":"stepped"},{"time":1.1666,"x":0,"y":0,"curve":"stepped"},{"time":2.3333,"x":0,"y":0,"curve":"stepped"},{"time":3.5,"x":0,"y":0,"curve":"stepped"},{"time":4.6666,"x":0,"y":0}],"scale":[{"time":0,"x":1,"y":1,"curve":"stepped"},{"time":1.1666,"x":1,"y":1,"curve":"stepped"},{"time":2.3333,"x":1,"y":1,"curve":"stepped"},{"time":3.5,"x":1,"y":1,"curve":"stepped"},{"time":4.6666,"x":1,"y":1}]}},"slots":{"bone":{"attachment":[{"time":0,"name":null},{"time":1.1666,"name":null},{"time":2.3333,"name":null},{"time":3.5,"name":null},{"time":4.6666,"name":null}]},"dragon_pet_wind6a_armor":{"attachment":[{"time":0,"name":"dragon_pet_wind6a_armor"},{"time":1.1666,"name":"dragon_pet_wind6a_armor"},{"time":2.3333,"name":"dragon_pet_wind6a_armor"},{"time":3.5,"name":"dragon_pet_wind6a_armor"},{"time":4.6666,"name":"dragon_pet_wind6a_armor"}]},"dragon_pet_wind6a_armor2":{"attachment":[{"time":0,"name":"dragon_pet_wind6a_armor"},{"time":1.1666,"name":"dragon_pet_wind6a_armor"},{"time":2.3333,"name":"dragon_pet_wind6a_armor"},{"time":3.5,"name":"dragon_pet_wind6a_armor"},{"time":4.6666,"name":"dragon_pet_wind6a_armor"}]},"dragon_pet_wind6a_body":{"attachment":[{"time":0,"name":"dragon_pet_wind6a_body"},{"time":1.1666,"name":"dragon_pet_wind6a_body"},{"time":2.3333,"name":"dragon_pet_wind6a_body"},{"time":3.5,"name":"dragon_pet_wind6a_body"},{"time":4.6666,"name":"dragon_pet_wind6a_body"}]},"dragon_pet_wind6a_eye":{"attachment":[{"time":0,"name":"dragon_pet_wind6a_eye"},{"time":1.1666,"name":"dragon_pet_wind6a_eye"},{"time":1.6666,"name":null},{"time":1.8333,"name":"dragon_pet_wind6a_eye"},{"time":2.3333,"name":"dragon_pet_wind6a_eye"},{"time":3.5,"name":"dragon_pet_wind6a_eye"},{"time":4.6666,"name":"dragon_pet_wind6a_eye"}]},"dragon_pet_wind6a_hand1":{"attachment":[{"time":0,"name":"dragon_pet_wind6a_hand1"},{"time":1.1666,"name":"dragon_pet_wind6a_hand1"},{"time":2.3333,"name":"dragon_pet_wind6a_hand1"},{"time":3.5,"name":"dragon_pet_wind6a_hand1"},{"time":4.6666,"name":"dragon_pet_wind6a_hand1"}]},"dragon_pet_wind6a_hand2":{"attachment":[{"time":0,"name":"dragon_pet_wind6a_hand2"},{"time":1.1666,"name":"dragon_pet_wind6a_hand2"},{"time":2.3333,"name":"dragon_pet_wind6a_hand2"},{"time":3.5,"name":"dragon_pet_wind6a_hand2"},{"time":4.6666,"name":"dragon_pet_wind6a_hand2"}]}}}}}