{
    "skeleton": {
        "hash": "nJei2prqmg7Cjzp9UHj7OTmLyqA",
        "spine": "3.0.09",
        "width": 330.99,
        "height": 207.5,
        "images": ""
    },
    "bones": [
        {
            "name": "root"
        },
        {
            "name": "center",
            "parent": "root",
            "y": -142.3,
            "scaleX": 0.5,
            "scaleY": 0.5
        },
        {
            "name": "bone",
            "parent": "center",
            "x": 114.8,
            "y": 185.69
        },
        {
            "name": "body",
            "parent": "bone",
            "length": 154.65,
            "rotation": 176.86
        },
        {
            "name": "leg2",
            "parent": "body",
            "length": 84.67,
            "x": 57.81,
            "y": -12.22,
            "rotation": 104.69
        },
        {
            "name": "leg22",
            "parent": "leg2",
            "length": 74.32,
            "x": 83.92,
            "y": 0.08,
            "rotation": -18.77
        },
        {
            "name": "leg1",
            "parent": "body",
            "length": 79.76,
            "rotation": 122.19
        },
        {
            "name": "leg11",
            "parent": "leg1",
            "length": 91.61,
            "x": 80.04,
            "y": 0.09,
            "rotation": -12.02
        },
        {
            "name": "head",
            "parent": "body",
            "length": 55.38,
            "x": 240.78,
            "y": -90.36,
            "rotation": 27.06
        },
        {
            "name": "hair2",
            "parent": "body",
            "length": 105.94,
            "x": 177.4,
            "y": -99.25,
            "rotation": 143.74
        },
        {
            "name": "arm2",
            "parent": "body",
            "length": 133.56,
            "x": 163.97,
            "y": 26.66,
            "rotation": 69.99
        },
        {
            "name": "arm1",
            "parent": "body",
            "length": 190.56,
            "x": 112.17,
            "y": 3.05,
            "rotation": 91.97
        },
        {
            "name": "tail",
            "parent": "body",
            "length": 107.39,
            "x": -37.88,
            "y": -5.91,
            "rotation": 148.94
        },
        {
            "name": "wing1",
            "parent": "body",
            "length": 269.09,
            "x": 112.37,
            "y": -68.15,
            "rotation": -165.12
        },
        {
            "name": "wing2",
            "parent": "body",
            "length": 173.97,
            "x": 142.33,
            "y": -67.28,
            "rotation": -137.8
        },
        {
            "name": "wing11",
            "parent": "wing1",
            "length": 100.34,
            "x": 106.24,
            "y": 80.68,
            "rotation": -11.75
        }
    ],
    "slots": [
        {
            "name": "leg22",
            "bone": "leg22",
            "attachment": "leg22"
        },
        {
            "name": "leg2",
            "bone": "leg2",
            "attachment": "leg2"
        },
        {
            "name": "tail",
            "bone": "tail",
            "attachment": "tail"
        },
        {
            "name": "wing2",
            "bone": "wing2",
            "attachment": "wing2"
        },
        {
            "name": "arm2",
            "bone": "arm2",
            "attachment": "arm2"
        },
        {
            "name": "body",
            "bone": "body",
            "attachment": "body"
        },
        {
            "name": "leg11",
            "bone": "leg11",
            "attachment": "leg11"
        },
        {
            "name": "leg1",
            "bone": "leg1",
            "attachment": "leg1"
        },
        {
            "name": "arm1",
            "bone": "arm1",
            "attachment": "arm1"
        },
        {
            "name": "head",
            "bone": "head",
            "attachment": "head"
        },
        {
            "name": "wing1",
            "bone": "wing1",
            "attachment": "wing1"
        },
        {
            "name": "hair",
            "bone": "hair2",
            "attachment": "hair"
        },
        {
            "name": "wing11",
            "bone": "wing11",
            "attachment": "wing11"
        }
    ],
    "skins": {
        "default": {
            "arm1": {
                "arm1": {
                    "x": 76.04,
                    "y": 8.4,
                    "rotation": 91.16,
                    "width": 118,
                    "height": 225
                }
            },
            "arm2": {
                "arm2": {
                    "x": 72.33,
                    "y": -23.06,
                    "rotation": 113.13,
                    "width": 155,
                    "height": 155
                }
            },
            "body": {
                "body": {
                    "x": 113.07,
                    "y": -38.25,
                    "rotation": -176.86,
                    "width": 305,
                    "height": 208
                }
            },
            "hair": {
                "hair": {
                    "x": 61.07,
                    "y": -9.91,
                    "rotation": 39.39,
                    "width": 109,
                    "height": 132
                }
            },
            "head": {
                "head": {
                    "x": -32.48,
                    "y": -22.23,
                    "rotation": 156.07,
                    "width": 169,
                    "height": 157
                },
                "head_att": {
                    "x": -30.86,
                    "y": -18.57,
                    "rotation": 156.07,
                    "width": 169,
                    "height": 165
                }
            },
            "leg1": {
                "leg1": {
                    "x": 31.91,
                    "y": 8.78,
                    "rotation": 60.93,
                    "width": 111,
                    "height": 148
                }
            },
            "leg11": {
                "leg11": {
                    "x": 49.97,
                    "y": -1.5,
                    "rotation": 72.93,
                    "width": 103,
                    "height": 125
                }
            },
            "leg2": {
                "leg2": {
                    "x": 29.84,
                    "y": -1.25,
                    "rotation": 78.44,
                    "width": 102,
                    "height": 153
                }
            },
            "leg22": {
                "leg22": {
                    "x": 39.26,
                    "y": -9.3,
                    "rotation": 97.19,
                    "width": 118,
                    "height": 114
                }
            },
            "tail": {
                "tail": {
                    "x": 153.97,
                    "y": 44.8,
                    "rotation": 34.18,
                    "width": 344,
                    "height": 180
                }
            },
            "wing1": {
                "wing1": {
                    "x": 131.65,
                    "y": -6.26,
                    "rotation": -11.75,
                    "width": 276,
                    "height": 247
                }
            },
            "wing11": {
                "wing11": {
                    "x": 46.06,
                    "y": -112.48,
                    "rotation": -0.02,
                    "width": 97,
                    "height": 260
                }
            },
            "wing2": {
                "wing2": {
                    "x": 50.02,
                    "y": -22.69,
                    "rotation": -39.08,
                    "width": 122,
                    "height": 281
                }
            }
        }
    },
    "animations": {
        "att": {
            "slots": {
                "head": {
                    "attachment": [
                        {
                            "time": 0,
                            "name": "head_att"
                        }
                    ]
                }
            },
            "bones": {
                "body": {
                    "rotate": [
                        {
                            "time": 0,
                            "angle": 0
                        }
                    ],
                    "translate": [
                        {
                            "time": 0,
                            "x": -9.32,
                            "y": 5.93
                        }
                    ],
                    "scale": [
                        {
                            "time": 0,
                            "x": 1,
                            "y": 1
                        }
                    ]
                },
                "wing2": {
                    "rotate": [
                        {
                            "time": 0,
                            "angle": -3.89
                        }
                    ],
                    "translate": [
                        {
                            "time": 0,
                            "x": 0,
                            "y": 0
                        }
                    ],
                    "scale": [
                        {
                            "time": 0,
                            "x": 1.066,
                            "y": 1
                        }
                    ]
                },
                "arm1": {
                    "rotate": [
                        {
                            "time": 0,
                            "angle": 4.08
                        }
                    ],
                    "translate": [
                        {
                            "time": 0,
                            "x": 0,
                            "y": 0
                        }
                    ],
                    "scale": [
                        {
                            "time": 0,
                            "x": 1.025,
                            "y": 1
                        }
                    ]
                },
                "arm2": {
                    "rotate": [
                        {
                            "time": 0,
                            "angle": 4.08
                        }
                    ],
                    "translate": [
                        {
                            "time": 0,
                            "x": 0,
                            "y": 0
                        }
                    ],
                    "scale": [
                        {
                            "time": 0,
                            "x": 1.025,
                            "y": 1
                        }
                    ]
                },
                "leg1": {
                    "rotate": [
                        {
                            "time": 0,
                            "angle": 4.08
                        }
                    ],
                    "translate": [
                        {
                            "time": 0,
                            "x": 0,
                            "y": 0
                        }
                    ],
                    "scale": [
                        {
                            "time": 0,
                            "x": 1.025,
                            "y": 1
                        }
                    ]
                },
                "leg11": {
                    "rotate": [
                        {
                            "time": 0,
                            "angle": 0
                        }
                    ],
                    "translate": [
                        {
                            "time": 0,
                            "x": 0,
                            "y": 0
                        }
                    ],
                    "scale": [
                        {
                            "time": 0,
                            "x": 1,
                            "y": 1
                        }
                    ]
                },
                "leg2": {
                    "rotate": [
                        {
                            "time": 0,
                            "angle": 4.08
                        }
                    ],
                    "translate": [
                        {
                            "time": 0,
                            "x": 0,
                            "y": 0
                        }
                    ],
                    "scale": [
                        {
                            "time": 0,
                            "x": 1.025,
                            "y": 1
                        }
                    ]
                },
                "leg22": {
                    "rotate": [
                        {
                            "time": 0,
                            "angle": 0
                        }
                    ],
                    "translate": [
                        {
                            "time": 0,
                            "x": 0,
                            "y": 0
                        }
                    ],
                    "scale": [
                        {
                            "time": 0,
                            "x": 1,
                            "y": 1
                        }
                    ]
                },
                "tail": {
                    "rotate": [
                        {
                            "time": 0,
                            "angle": -13.27
                        }
                    ],
                    "translate": [
                        {
                            "time": 0,
                            "x": 0,
                            "y": 0
                        }
                    ],
                    "scale": [
                        {
                            "time": 0,
                            "x": 1,
                            "y": 1
                        }
                    ]
                },
                "head": {
                    "rotate": [
                        {
                            "time": 0,
                            "angle": -16.55
                        }
                    ],
                    "translate": [
                        {
                            "time": 0,
                            "x": 0,
                            "y": 0
                        }
                    ],
                    "scale": [
                        {
                            "time": 0,
                            "x": 1,
                            "y": 1
                        }
                    ]
                },
                "hair2": {
                    "rotate": [
                        {
                            "time": 0,
                            "angle": -5.22
                        }
                    ],
                    "translate": [
                        {
                            "time": 0,
                            "x": 0,
                            "y": 0
                        }
                    ],
                    "scale": [
                        {
                            "time": 0,
                            "x": 1,
                            "y": 1
                        }
                    ]
                },
                "wing1": {
                    "rotate": [
                        {
                            "time": 0,
                            "angle": -3.89
                        }
                    ],
                    "translate": [
                        {
                            "time": 0,
                            "x": 0,
                            "y": 0
                        }
                    ],
                    "scale": [
                        {
                            "time": 0,
                            "x": 1.066,
                            "y": 1
                        }
                    ]
                },
                "wing11": {
                    "rotate": [
                        {
                            "time": 0,
                            "angle": -2.35
                        }
                    ],
                    "translate": [
                        {
                            "time": 0,
                            "x": 0,
                            "y": 0
                        }
                    ],
                    "scale": [
                        {
                            "time": 0,
                            "x": 1.066,
                            "y": 1
                        }
                    ]
                },
                "bone": {
                    "rotate": [
                        {
                            "time": 0,
                            "angle": 0
                        }
                    ],
                    "translate": [
                        {
                            "time": 0,
                            "x": 0,
                            "y": 0
                        }
                    ],
                    "scale": [
                        {
                            "time": 0,
                            "x": 1,
                            "y": 1
                        }
                    ]
                }
            }
        },
        "wait": {
            "slots": {
                "head": {
                    "attachment": [
                        {
                            "time": 1.3333,
                            "name": "head_att"
                        },
                        {
                            "time": 2.6666,
                            "name": "head"
                        }
                    ]
                }
            },
            "bones": {
                "leg22": {
                    "rotate": [
                        {
                            "time": 0,
                            "angle": 0,
                            "curve": [
                                0.25,
                                0,
                                0.75,
                                1
                            ]
                        },
                        {
                            "time": 1,
                            "angle": 0.08,
                            "curve": [
                                0.686,
                                0.07,
                                0.935,
                                0.78
                            ]
                        },
                        {
                            "time": 1.3333,
                            "angle": 0,
                            "curve": [
                                0.718,
                                0,
                                0.75,
                                1
                            ]
                        },
                        {
                            "time": 2.6666,
                            "angle": -0.9,
                            "curve": [
                                0.25,
                                0,
                                0.75,
                                1
                            ]
                        },
                        {
                            "time": 3.6666,
                            "angle": 0
                        }
                    ],
                    "translate": [
                        {
                            "time": 0,
                            "x": 0,
                            "y": 0,
                            "curve": "stepped"
                        },
                        {
                            "time": 1,
                            "x": 0,
                            "y": 0,
                            "curve": "stepped"
                        },
                        {
                            "time": 1.3333,
                            "x": 0,
                            "y": 0,
                            "curve": "stepped"
                        },
                        {
                            "time": 2.6666,
                            "x": 0,
                            "y": 0,
                            "curve": "stepped"
                        },
                        {
                            "time": 3.6666,
                            "x": 0,
                            "y": 0
                        }
                    ],
                    "scale": [
                        {
                            "time": 0,
                            "x": 1,
                            "y": 1,
                            "curve": "stepped"
                        },
                        {
                            "time": 1,
                            "x": 1,
                            "y": 1,
                            "curve": "stepped"
                        },
                        {
                            "time": 1.3333,
                            "x": 1,
                            "y": 1,
                            "curve": "stepped"
                        },
                        {
                            "time": 2.6666,
                            "x": 1,
                            "y": 1,
                            "curve": "stepped"
                        },
                        {
                            "time": 3.6666,
                            "x": 1,
                            "y": 1
                        }
                    ]
                },
                "arm2": {
                    "rotate": [
                        {
                            "time": 0,
                            "angle": 0,
                            "curve": [
                                0.25,
                                0,
                                0.75,
                                1
                            ]
                        },
                        {
                            "time": 1,
                            "angle": -4.88,
                            "curve": [
                                0.686,
                                0.07,
                                0.935,
                                0.78
                            ]
                        },
                        {
                            "time": 1.3333,
                            "angle": 4.08,
                            "curve": [
                                0.718,
                                0,
                                0.75,
                                1
                            ]
                        },
                        {
                            "time": 2.6666,
                            "angle": -0.9,
                            "curve": [
                                0.25,
                                0,
                                0.75,
                                1
                            ]
                        },
                        {
                            "time": 3.6666,
                            "angle": 0
                        }
                    ],
                    "translate": [
                        {
                            "time": 0,
                            "x": 0,
                            "y": 0,
                            "curve": "stepped"
                        },
                        {
                            "time": 1,
                            "x": 0,
                            "y": 0,
                            "curve": "stepped"
                        },
                        {
                            "time": 1.3333,
                            "x": 0,
                            "y": 0,
                            "curve": "stepped"
                        },
                        {
                            "time": 2.6666,
                            "x": 0,
                            "y": 0,
                            "curve": "stepped"
                        },
                        {
                            "time": 3.6666,
                            "x": 0,
                            "y": 0
                        }
                    ],
                    "scale": [
                        {
                            "time": 0,
                            "x": 1,
                            "y": 1,
                            "curve": [
                                0.25,
                                0,
                                0.75,
                                1
                            ]
                        },
                        {
                            "time": 1,
                            "x": 0.941,
                            "y": 1,
                            "curve": [
                                0.686,
                                0.07,
                                0.935,
                                0.78
                            ]
                        },
                        {
                            "time": 1.3333,
                            "x": 1.025,
                            "y": 1,
                            "curve": [
                                0.718,
                                0,
                                0.75,
                                1
                            ]
                        },
                        {
                            "time": 2.6666,
                            "x": 0.968,
                            "y": 1,
                            "curve": [
                                0.25,
                                0,
                                0.75,
                                1
                            ]
                        },
                        {
                            "time": 3.6666,
                            "x": 1,
                            "y": 1
                        }
                    ]
                },
                "arm1": {
                    "rotate": [
                        {
                            "time": 0,
                            "angle": 0,
                            "curve": [
                                0.25,
                                0,
                                0.75,
                                1
                            ]
                        },
                        {
                            "time": 1,
                            "angle": -2.83,
                            "curve": [
                                0.686,
                                0.07,
                                0.935,
                                0.78
                            ]
                        },
                        {
                            "time": 1.3333,
                            "angle": 4.08,
                            "curve": [
                                0.718,
                                0,
                                0.75,
                                1
                            ]
                        },
                        {
                            "time": 2.6666,
                            "angle": -0.9,
                            "curve": [
                                0.25,
                                0,
                                0.75,
                                1
                            ]
                        },
                        {
                            "time": 3.6666,
                            "angle": 0
                        }
                    ],
                    "translate": [
                        {
                            "time": 0,
                            "x": 0,
                            "y": 0,
                            "curve": "stepped"
                        },
                        {
                            "time": 1,
                            "x": 0,
                            "y": 0,
                            "curve": "stepped"
                        },
                        {
                            "time": 1.3333,
                            "x": 0,
                            "y": 0,
                            "curve": "stepped"
                        },
                        {
                            "time": 2.6666,
                            "x": 0,
                            "y": 0,
                            "curve": "stepped"
                        },
                        {
                            "time": 3.6666,
                            "x": 0,
                            "y": 0
                        }
                    ],
                    "scale": [
                        {
                            "time": 0,
                            "x": 1,
                            "y": 1,
                            "curve": [
                                0.25,
                                0,
                                0.75,
                                1
                            ]
                        },
                        {
                            "time": 1,
                            "x": 0.966,
                            "y": 1,
                            "curve": [
                                0.686,
                                0.07,
                                0.935,
                                0.78
                            ]
                        },
                        {
                            "time": 1.3333,
                            "x": 1.025,
                            "y": 1,
                            "curve": [
                                0.718,
                                0,
                                0.75,
                                1
                            ]
                        },
                        {
                            "time": 2.6666,
                            "x": 0.968,
                            "y": 1,
                            "curve": [
                                0.25,
                                0,
                                0.75,
                                1
                            ]
                        },
                        {
                            "time": 3.6666,
                            "x": 1,
                            "y": 1
                        }
                    ]
                },
                "leg11": {
                    "rotate": [
                        {
                            "time": 0,
                            "angle": 0,
                            "curve": [
                                0.25,
                                0,
                                0.75,
                                1
                            ]
                        },
                        {
                            "time": 1,
                            "angle": -0.36,
                            "curve": [
                                0.686,
                                0.07,
                                0.935,
                                0.78
                            ]
                        },
                        {
                            "time": 1.3333,
                            "angle": 0,
                            "curve": [
                                0.718,
                                0,
                                0.75,
                                1
                            ]
                        },
                        {
                            "time": 2.6666,
                            "angle": -0.9,
                            "curve": [
                                0.25,
                                0,
                                0.75,
                                1
                            ]
                        },
                        {
                            "time": 3.6666,
                            "angle": 0
                        }
                    ],
                    "translate": [
                        {
                            "time": 0,
                            "x": 0,
                            "y": 0,
                            "curve": "stepped"
                        },
                        {
                            "time": 1,
                            "x": 0,
                            "y": 0,
                            "curve": "stepped"
                        },
                        {
                            "time": 1.3333,
                            "x": 0,
                            "y": 0,
                            "curve": "stepped"
                        },
                        {
                            "time": 2.6666,
                            "x": 0,
                            "y": 0,
                            "curve": "stepped"
                        },
                        {
                            "time": 3.6666,
                            "x": 0,
                            "y": 0
                        }
                    ],
                    "scale": [
                        {
                            "time": 0,
                            "x": 1,
                            "y": 1,
                            "curve": "stepped"
                        },
                        {
                            "time": 1,
                            "x": 1,
                            "y": 1,
                            "curve": "stepped"
                        },
                        {
                            "time": 1.3333,
                            "x": 1,
                            "y": 1,
                            "curve": "stepped"
                        },
                        {
                            "time": 2.6666,
                            "x": 1,
                            "y": 1,
                            "curve": "stepped"
                        },
                        {
                            "time": 3.6666,
                            "x": 1,
                            "y": 1
                        }
                    ]
                },
                "leg2": {
                    "rotate": [
                        {
                            "time": 0,
                            "angle": 0,
                            "curve": [
                                0.25,
                                0,
                                0.75,
                                1
                            ]
                        },
                        {
                            "time": 1,
                            "angle": -1.86,
                            "curve": [
                                0.686,
                                0.07,
                                0.935,
                                0.78
                            ]
                        },
                        {
                            "time": 1.3333,
                            "angle": 4.08,
                            "curve": [
                                0.718,
                                0,
                                0.75,
                                1
                            ]
                        },
                        {
                            "time": 2.6666,
                            "angle": 0.77,
                            "curve": [
                                0.25,
                                0,
                                0.75,
                                1
                            ]
                        },
                        {
                            "time": 3.6666,
                            "angle": 0
                        }
                    ],
                    "translate": [
                        {
                            "time": 0,
                            "x": 0,
                            "y": 0,
                            "curve": "stepped"
                        },
                        {
                            "time": 1,
                            "x": 0,
                            "y": 0,
                            "curve": "stepped"
                        },
                        {
                            "time": 1.3333,
                            "x": 0,
                            "y": 0,
                            "curve": "stepped"
                        },
                        {
                            "time": 2.6666,
                            "x": 0,
                            "y": 0,
                            "curve": "stepped"
                        },
                        {
                            "time": 3.6666,
                            "x": 0,
                            "y": 0
                        }
                    ],
                    "scale": [
                        {
                            "time": 0,
                            "x": 1,
                            "y": 1,
                            "curve": [
                                0.25,
                                0,
                                0.75,
                                1
                            ]
                        },
                        {
                            "time": 1,
                            "x": 0.971,
                            "y": 1,
                            "curve": [
                                0.686,
                                0.07,
                                0.935,
                                0.78
                            ]
                        },
                        {
                            "time": 1.3333,
                            "x": 1.025,
                            "y": 1,
                            "curve": [
                                0.718,
                                0,
                                0.75,
                                1
                            ]
                        },
                        {
                            "time": 2.6666,
                            "x": 0.959,
                            "y": 1,
                            "curve": [
                                0.25,
                                0,
                                0.75,
                                1
                            ]
                        },
                        {
                            "time": 3.6666,
                            "x": 1,
                            "y": 1
                        }
                    ]
                },
                "head": {
                    "rotate": [
                        {
                            "time": 0,
                            "angle": 0.4,
                            "curve": [
                                0.374,
                                0.61,
                                0.715,
                                1
                            ]
                        },
                        {
                            "time": 0.1333,
                            "angle": 0,
                            "curve": [
                                0.718,
                                0,
                                0.75,
                                1
                            ]
                        },
                        {
                            "time": 1.1333,
                            "angle": 8.78,
                            "curve": [
                                0.25,
                                0,
                                0.75,
                                1
                            ]
                        },
                        {
                            "time": 1.4666,
                            "angle": -16.55,
                            "curve": [
                                0.25,
                                0,
                                0.75,
                                1
                            ]
                        },
                        {
                            "time": 2.8,
                            "angle": 3.14,
                            "curve": [
                                0.242,
                                0,
                                0.679,
                                0.71
                            ]
                        },
                        {
                            "time": 3.6666,
                            "angle": 0.4
                        }
                    ],
                    "translate": [
                        {
                            "time": 0,
                            "x": -0.05,
                            "y": 1,
                            "curve": [
                                0.303,
                                0.61,
                                0.618,
                                1
                            ]
                        },
                        {
                            "time": 0.1333,
                            "x": 0,
                            "y": 0,
                            "curve": [
                                0.25,
                                0,
                                0.75,
                                1
                            ]
                        },
                        {
                            "time": 1.1333,
                            "x": -0.04,
                            "y": 7.63,
                            "curve": [
                                0.25,
                                0,
                                0.75,
                                1
                            ]
                        },
                        {
                            "time": 1.4666,
                            "x": 0,
                            "y": 0,
                            "curve": [
                                0.25,
                                0,
                                0.75,
                                1
                            ]
                        },
                        {
                            "time": 2.8,
                            "x": -0.21,
                            "y": 4.23,
                            "curve": [
                                0.661,
                                0,
                                0.816,
                                0.71
                            ]
                        },
                        {
                            "time": 3.6666,
                            "x": -0.05,
                            "y": 1
                        }
                    ],
                    "scale": [
                        {
                            "time": 0,
                            "x": 1,
                            "y": 1,
                            "curve": "stepped"
                        },
                        {
                            "time": 0.1333,
                            "x": 1,
                            "y": 1,
                            "curve": "stepped"
                        },
                        {
                            "time": 1.1333,
                            "x": 1,
                            "y": 1,
                            "curve": "stepped"
                        },
                        {
                            "time": 1.4666,
                            "x": 1,
                            "y": 1,
                            "curve": "stepped"
                        },
                        {
                            "time": 2.8,
                            "x": 1,
                            "y": 1,
                            "curve": "stepped"
                        },
                        {
                            "time": 3.6666,
                            "x": 1,
                            "y": 1
                        }
                    ]
                },
                "leg1": {
                    "rotate": [
                        {
                            "time": 0,
                            "angle": 0,
                            "curve": [
                                0.25,
                                0,
                                0.75,
                                1
                            ]
                        },
                        {
                            "time": 1,
                            "angle": -1.86,
                            "curve": [
                                0.686,
                                0.07,
                                0.935,
                                0.78
                            ]
                        },
                        {
                            "time": 1.3333,
                            "angle": 4.08,
                            "curve": [
                                0.718,
                                0,
                                0.75,
                                1
                            ]
                        },
                        {
                            "time": 2.6666,
                            "angle": 0.77,
                            "curve": [
                                0.25,
                                0,
                                0.75,
                                1
                            ]
                        },
                        {
                            "time": 3.6666,
                            "angle": 0
                        }
                    ],
                    "translate": [
                        {
                            "time": 0,
                            "x": 0,
                            "y": 0,
                            "curve": "stepped"
                        },
                        {
                            "time": 1,
                            "x": 0,
                            "y": 0,
                            "curve": "stepped"
                        },
                        {
                            "time": 1.3333,
                            "x": 0,
                            "y": 0,
                            "curve": "stepped"
                        },
                        {
                            "time": 2.6666,
                            "x": 0,
                            "y": 0,
                            "curve": "stepped"
                        },
                        {
                            "time": 3.6666,
                            "x": 0,
                            "y": 0
                        }
                    ],
                    "scale": [
                        {
                            "time": 0,
                            "x": 1,
                            "y": 1,
                            "curve": [
                                0.25,
                                0,
                                0.75,
                                1
                            ]
                        },
                        {
                            "time": 1,
                            "x": 0.976,
                            "y": 1,
                            "curve": [
                                0.686,
                                0.07,
                                0.935,
                                0.78
                            ]
                        },
                        {
                            "time": 1.3333,
                            "x": 1.025,
                            "y": 1,
                            "curve": [
                                0.718,
                                0,
                                0.75,
                                1
                            ]
                        },
                        {
                            "time": 2.6666,
                            "x": 0.959,
                            "y": 1,
                            "curve": [
                                0.25,
                                0,
                                0.75,
                                1
                            ]
                        },
                        {
                            "time": 3.6666,
                            "x": 1,
                            "y": 1
                        }
                    ]
                },
                "body": {
                    "rotate": [
                        {
                            "time": 0,
                            "angle": 0,
                            "curve": [
                                0.25,
                                0,
                                0.75,
                                1
                            ]
                        },
                        {
                            "time": 1,
                            "angle": 2.82,
                            "curve": [
                                0.686,
                                0.07,
                                0.935,
                                0.78
                            ]
                        },
                        {
                            "time": 1.3333,
                            "angle": 0,
                            "curve": [
                                0.718,
                                0,
                                0.75,
                                1
                            ]
                        },
                        {
                            "time": 2.6666,
                            "angle": 0.27,
                            "curve": [
                                0.25,
                                0,
                                0.75,
                                1
                            ]
                        },
                        {
                            "time": 3.6666,
                            "angle": 0
                        }
                    ],
                    "translate": [
                        {
                            "time": 0,
                            "x": 0,
                            "y": 0,
                            "curve": [
                                0.25,
                                0,
                                0.75,
                                1
                            ]
                        },
                        {
                            "time": 1,
                            "x": 0,
                            "y": -3.39,
                            "curve": [
                                0.686,
                                0.07,
                                0.935,
                                0.78
                            ]
                        },
                        {
                            "time": 1.3333,
                            "x": -9.32,
                            "y": 5.93,
                            "curve": [
                                0.718,
                                0,
                                0.75,
                                1
                            ]
                        },
                        {
                            "time": 2.6666,
                            "x": 0,
                            "y": -5.93,
                            "curve": [
                                0.25,
                                0,
                                0.75,
                                1
                            ]
                        },
                        {
                            "time": 3.6666,
                            "x": 0,
                            "y": 0
                        }
                    ],
                    "scale": [
                        {
                            "time": 0,
                            "x": 1,
                            "y": 1,
                            "curve": "stepped"
                        },
                        {
                            "time": 1,
                            "x": 1,
                            "y": 1,
                            "curve": "stepped"
                        },
                        {
                            "time": 1.3333,
                            "x": 1,
                            "y": 1,
                            "curve": "stepped"
                        },
                        {
                            "time": 2.6666,
                            "x": 1,
                            "y": 1,
                            "curve": "stepped"
                        },
                        {
                            "time": 3.6666,
                            "x": 1,
                            "y": 1
                        }
                    ]
                },
                "hair2": {
                    "rotate": [
                        {
                            "time": 0,
                            "angle": 0.2,
                            "curve": [
                                0.372,
                                0.62,
                                0.711,
                                1
                            ]
                        },
                        {
                            "time": 0.2,
                            "angle": 0,
                            "curve": [
                                0.368,
                                0.62,
                                0.706,
                                1
                            ]
                        },
                        {
                            "time": 1.2,
                            "angle": 4.92,
                            "curve": [
                                0.243,
                                0,
                                0.694,
                                0.76
                            ]
                        },
                        {
                            "time": 1.5333,
                            "angle": -5.22,
                            "curve": [
                                0.304,
                                0,
                                0.64,
                                0.35
                            ]
                        },
                        {
                            "time": 1.8666,
                            "angle": -4.02,
                            "curve": [
                                0.289,
                                0.16,
                                0.754,
                                1
                            ]
                        },
                        {
                            "time": 2.2,
                            "angle": -5.22,
                            "curve": [
                                0.304,
                                0,
                                0.64,
                                0.35
                            ]
                        },
                        {
                            "time": 2.5333,
                            "angle": -4.02,
                            "curve": [
                                0.289,
                                0.16,
                                0.754,
                                1
                            ]
                        },
                        {
                            "time": 2.8666,
                            "angle": -5.22,
                            "curve": [
                                0.304,
                                0,
                                0.64,
                                0.35
                            ]
                        },
                        {
                            "time": 3.6666,
                            "angle": 0.2
                        }
                    ],
                    "translate": [
                        {
                            "time": 0,
                            "x": 0,
                            "y": 0,
                            "curve": "stepped"
                        },
                        {
                            "time": 0.2,
                            "x": 0,
                            "y": 0,
                            "curve": "stepped"
                        },
                        {
                            "time": 1.2,
                            "x": 0,
                            "y": 0,
                            "curve": "stepped"
                        },
                        {
                            "time": 1.5333,
                            "x": 0,
                            "y": 0,
                            "curve": "stepped"
                        },
                        {
                            "time": 2.8666,
                            "x": 0,
                            "y": 0,
                            "curve": "stepped"
                        },
                        {
                            "time": 3.6666,
                            "x": 0,
                            "y": 0
                        }
                    ],
                    "scale": [
                        {
                            "time": 0,
                            "x": 1,
                            "y": 1,
                            "curve": "stepped"
                        },
                        {
                            "time": 0.2,
                            "x": 1,
                            "y": 1,
                            "curve": "stepped"
                        },
                        {
                            "time": 1.2,
                            "x": 1,
                            "y": 1,
                            "curve": "stepped"
                        },
                        {
                            "time": 1.5333,
                            "x": 1,
                            "y": 1,
                            "curve": "stepped"
                        },
                        {
                            "time": 2.8666,
                            "x": 1,
                            "y": 1,
                            "curve": "stepped"
                        },
                        {
                            "time": 3.6666,
                            "x": 1,
                            "y": 1
                        }
                    ]
                },
                "wing11": {
                    "rotate": [
                        {
                            "time": 0,
                            "angle": 0.39,
                            "curve": [
                                0.303,
                                0.61,
                                0.618,
                                1
                            ]
                        },
                        {
                            "time": 0.1333,
                            "angle": 0,
                            "curve": [
                                0.25,
                                0,
                                0.75,
                                1
                            ]
                        },
                        {
                            "time": 1.1333,
                            "angle": 4.02,
                            "curve": [
                                0.25,
                                0,
                                0.75,
                                1
                            ]
                        },
                        {
                            "time": 1.4666,
                            "angle": -2.35,
                            "curve": [
                                0.374,
                                0.61,
                                0.715,
                                1
                            ]
                        },
                        {
                            "time": 2.8,
                            "angle": 1.66,
                            "curve": [
                                0.661,
                                0,
                                0.816,
                                0.71
                            ]
                        },
                        {
                            "time": 3.6666,
                            "angle": 0.39
                        }
                    ],
                    "translate": [
                        {
                            "time": 0,
                            "x": 0,
                            "y": 0,
                            "curve": "stepped"
                        },
                        {
                            "time": 0.1333,
                            "x": 0,
                            "y": 0,
                            "curve": "stepped"
                        },
                        {
                            "time": 1.1333,
                            "x": 0,
                            "y": 0,
                            "curve": "stepped"
                        },
                        {
                            "time": 1.4666,
                            "x": 0,
                            "y": 0,
                            "curve": "stepped"
                        },
                        {
                            "time": 2.8,
                            "x": 0,
                            "y": 0,
                            "curve": "stepped"
                        },
                        {
                            "time": 3.6666,
                            "x": 0,
                            "y": 0
                        }
                    ],
                    "scale": [
                        {
                            "time": 0,
                            "x": 0.992,
                            "y": 1,
                            "curve": [
                                0.307,
                                0.63,
                                0.633,
                                1
                            ]
                        },
                        {
                            "time": 0.0666,
                            "x": 0.995,
                            "y": 1,
                            "curve": [
                                0.242,
                                0,
                                0.679,
                                0.71
                            ]
                        },
                        {
                            "time": 0.2,
                            "x": 1,
                            "y": 1,
                            "curve": [
                                0.25,
                                0,
                                0.75,
                                1
                            ]
                        },
                        {
                            "time": 1.2,
                            "x": 0.946,
                            "y": 1,
                            "curve": [
                                0.25,
                                0,
                                0.75,
                                1
                            ]
                        },
                        {
                            "time": 1.5333,
                            "x": 1.066,
                            "y": 1,
                            "curve": [
                                0.374,
                                0.61,
                                0.715,
                                1
                            ]
                        },
                        {
                            "time": 2.8666,
                            "x": 0.967,
                            "y": 1,
                            "curve": [
                                0.687,
                                0,
                                0.799,
                                0.8
                            ]
                        },
                        {
                            "time": 3.6666,
                            "x": 0.992,
                            "y": 1
                        }
                    ]
                },
                "wing2": {
                    "rotate": [
                        {
                            "time": 0,
                            "angle": 0.07,
                            "curve": [
                                0.359,
                                0.64,
                                0.695,
                                1
                            ]
                        },
                        {
                            "time": 0.0666,
                            "angle": 0,
                            "curve": [
                                0.686,
                                0.07,
                                0.935,
                                0.78
                            ]
                        },
                        {
                            "time": 1.0666,
                            "angle": 4.97,
                            "curve": [
                                0.25,
                                0,
                                0.75,
                                1
                            ]
                        },
                        {
                            "time": 1.4,
                            "angle": -3.89,
                            "curve": [
                                0.25,
                                0,
                                0.75,
                                1
                            ]
                        },
                        {
                            "time": 2.7333,
                            "angle": 1.7,
                            "curve": [
                                0.245,
                                0,
                                0.71,
                                0.83
                            ]
                        },
                        {
                            "time": 3.6666,
                            "angle": 0.07
                        }
                    ],
                    "translate": [
                        {
                            "time": 0,
                            "x": 0,
                            "y": 0,
                            "curve": "stepped"
                        },
                        {
                            "time": 0.0666,
                            "x": 0,
                            "y": 0,
                            "curve": "stepped"
                        },
                        {
                            "time": 1.0666,
                            "x": 0,
                            "y": 0,
                            "curve": "stepped"
                        },
                        {
                            "time": 1.4,
                            "x": 0,
                            "y": 0,
                            "curve": "stepped"
                        },
                        {
                            "time": 2.7333,
                            "x": 0,
                            "y": 0,
                            "curve": "stepped"
                        },
                        {
                            "time": 3.6666,
                            "x": 0,
                            "y": 0
                        }
                    ],
                    "scale": [
                        {
                            "time": 0,
                            "x": 0.993,
                            "y": 1.004,
                            "curve": [
                                0.351,
                                0.42,
                                0.686,
                                0.76
                            ]
                        },
                        {
                            "time": 0.0666,
                            "x": 0.997,
                            "y": 1.001,
                            "curve": [
                                0.25,
                                0,
                                0.75,
                                1
                            ]
                        },
                        {
                            "time": 0.1333,
                            "x": 1,
                            "y": 1,
                            "curve": [
                                0.359,
                                0.64,
                                0.695,
                                1
                            ]
                        },
                        {
                            "time": 1.1333,
                            "x": 0.822,
                            "y": 1,
                            "curve": [
                                0.359,
                                0.64,
                                0.695,
                                1
                            ]
                        },
                        {
                            "time": 1.4666,
                            "x": 1.066,
                            "y": 1,
                            "curve": [
                                0.686,
                                0.07,
                                0.935,
                                0.78
                            ]
                        },
                        {
                            "time": 2.8,
                            "x": 0.949,
                            "y": 1.035,
                            "curve": [
                                0.242,
                                0,
                                0.679,
                                0.71
                            ]
                        },
                        {
                            "time": 3.6666,
                            "x": 0.993,
                            "y": 1.004
                        }
                    ]
                },
                "tail": {
                    "rotate": [
                        {
                            "time": 0,
                            "angle": 0.44,
                            "curve": [
                                0.307,
                                0.6,
                                0.61,
                                1
                            ]
                        },
                        {
                            "time": 0.1666,
                            "angle": 0,
                            "curve": [
                                0.25,
                                0,
                                0.75,
                                1
                            ]
                        },
                        {
                            "time": 1.1666,
                            "angle": 6.73,
                            "curve": [
                                0.25,
                                0,
                                0.75,
                                1
                            ]
                        },
                        {
                            "time": 1.5,
                            "angle": -13.27,
                            "curve": [
                                0.25,
                                0,
                                0.75,
                                1
                            ]
                        },
                        {
                            "time": 2.8333,
                            "angle": 1.28,
                            "curve": [
                                0.642,
                                0,
                                0.823,
                                0.66
                            ]
                        },
                        {
                            "time": 3.6666,
                            "angle": 0.44
                        }
                    ],
                    "translate": [
                        {
                            "time": 0,
                            "x": 0.01,
                            "y": -0.29,
                            "curve": [
                                0.307,
                                0.6,
                                0.61,
                                1
                            ]
                        },
                        {
                            "time": 0.1666,
                            "x": 0,
                            "y": 0,
                            "curve": [
                                0.25,
                                0,
                                0.75,
                                1
                            ]
                        },
                        {
                            "time": 1.1666,
                            "x": 0.01,
                            "y": -3.39,
                            "curve": [
                                0.25,
                                0,
                                0.75,
                                1
                            ]
                        },
                        {
                            "time": 1.5,
                            "x": -0.18,
                            "y": 3.38,
                            "curve": [
                                0.25,
                                0,
                                0.75,
                                1
                            ]
                        },
                        {
                            "time": 2.8333,
                            "x": 0.04,
                            "y": -0.84,
                            "curve": [
                                0.642,
                                0,
                                0.823,
                                0.66
                            ]
                        },
                        {
                            "time": 3.6666,
                            "x": 0.01,
                            "y": -0.29
                        }
                    ],
                    "scale": [
                        {
                            "time": 0,
                            "x": 1,
                            "y": 1,
                            "curve": "stepped"
                        },
                        {
                            "time": 0.1666,
                            "x": 1,
                            "y": 1,
                            "curve": "stepped"
                        },
                        {
                            "time": 1.1666,
                            "x": 1,
                            "y": 1,
                            "curve": "stepped"
                        },
                        {
                            "time": 1.5,
                            "x": 1,
                            "y": 1,
                            "curve": "stepped"
                        },
                        {
                            "time": 2.8333,
                            "x": 1,
                            "y": 1,
                            "curve": "stepped"
                        },
                        {
                            "time": 3.6666,
                            "x": 1,
                            "y": 1
                        }
                    ]
                },
                "wing1": {
                    "rotate": [
                        {
                            "time": 0,
                            "angle": 0.07,
                            "curve": [
                                0.359,
                                0.64,
                                0.695,
                                1
                            ]
                        },
                        {
                            "time": 0.0666,
                            "angle": 0,
                            "curve": [
                                0.718,
                                0,
                                0.75,
                                1
                            ]
                        },
                        {
                            "time": 1.0666,
                            "angle": 4.97,
                            "curve": [
                                0.25,
                                0,
                                0.75,
                                1
                            ]
                        },
                        {
                            "time": 1.4,
                            "angle": -3.89,
                            "curve": [
                                0.686,
                                0.07,
                                0.935,
                                0.78
                            ]
                        },
                        {
                            "time": 2.7333,
                            "angle": 1.7,
                            "curve": [
                                0.245,
                                0,
                                0.71,
                                0.83
                            ]
                        },
                        {
                            "time": 3.6666,
                            "angle": 0.07
                        }
                    ],
                    "translate": [
                        {
                            "time": 0,
                            "x": 0,
                            "y": 0,
                            "curve": "stepped"
                        },
                        {
                            "time": 0.0666,
                            "x": 0,
                            "y": 0,
                            "curve": "stepped"
                        },
                        {
                            "time": 1.0666,
                            "x": 0,
                            "y": 0,
                            "curve": "stepped"
                        },
                        {
                            "time": 1.4,
                            "x": 0,
                            "y": 0,
                            "curve": "stepped"
                        },
                        {
                            "time": 2.7333,
                            "x": 0,
                            "y": 0,
                            "curve": "stepped"
                        },
                        {
                            "time": 3.6666,
                            "x": 0,
                            "y": 0
                        }
                    ],
                    "scale": [
                        {
                            "time": 0,
                            "x": 0.996,
                            "y": 1,
                            "curve": [
                                0.361,
                                0.64,
                                0.697,
                                1
                            ]
                        },
                        {
                            "time": 0.0666,
                            "x": 0.998,
                            "y": 1,
                            "curve": [
                                0.718,
                                0,
                                0.75,
                                1
                            ]
                        },
                        {
                            "time": 0.1333,
                            "x": 1,
                            "y": 1,
                            "curve": [
                                0.359,
                                0.64,
                                0.695,
                                1
                            ]
                        },
                        {
                            "time": 1.1333,
                            "x": 0.812,
                            "y": 1,
                            "curve": [
                                0.359,
                                0.64,
                                0.695,
                                1
                            ]
                        },
                        {
                            "time": 1.4666,
                            "x": 1.066,
                            "y": 1,
                            "curve": [
                                0.25,
                                0,
                                0.75,
                                1
                            ]
                        },
                        {
                            "time": 2.8,
                            "x": 0.967,
                            "y": 1,
                            "curve": [
                                0.244,
                                0,
                                0.706,
                                0.81
                            ]
                        },
                        {
                            "time": 3.6666,
                            "x": 0.996,
                            "y": 1
                        }
                    ]
                },
                "bone": {
                    "rotate": [
                        {
                            "time": 0,
                            "angle": 0,
                            "curve": "stepped"
                        },
                        {
                            "time": 3.6666,
                            "angle": 0
                        }
                    ],
                    "translate": [
                        {
                            "time": 0,
                            "x": 0,
                            "y": 0,
                            "curve": "stepped"
                        },
                        {
                            "time": 1.3333,
                            "x": 0,
                            "y": 0,
                            "curve": [
                                0.333,
                                0.33,
                                0.667,
                                0.66
                            ]
                        },
                        {
                            "time": 1.4333,
                            "x": -5.08,
                            "y": 0,
                            "curve": [
                                0.378,
                                0.52,
                                0.746,
                                1
                            ]
                        },
                        {
                            "time": 1.5666,
                            "x": 0,
                            "y": 0,
                            "curve": [
                                0.333,
                                0.33,
                                0.667,
                                0.66
                            ]
                        },
                        {
                            "time": 1.6666,
                            "x": -4.23,
                            "y": 0,
                            "curve": [
                                0.378,
                                0.52,
                                0.746,
                                1
                            ]
                        },
                        {
                            "time": 1.8,
                            "x": 0,
                            "y": 0,
                            "curve": [
                                0.333,
                                0.33,
                                0.667,
                                0.66
                            ]
                        },
                        {
                            "time": 1.9,
                            "x": -2.54,
                            "y": 0,
                            "curve": [
                                0.378,
                                0.52,
                                0.746,
                                1
                            ]
                        },
                        {
                            "time": 2,
                            "x": 0,
                            "y": 0,
                            "curve": "stepped"
                        },
                        {
                            "time": 3.6666,
                            "x": 0,
                            "y": 0
                        }
                    ],
                    "scale": [
                        {
                            "time": 0,
                            "x": 1,
                            "y": 1,
                            "curve": "stepped"
                        },
                        {
                            "time": 3.6666,
                            "x": 1,
                            "y": 1
                        }
                    ]
                }
            }
        }
    }
}